<?xml version="1.0" encoding="UTF-8"?>
<!DOCTYPE tv SYSTEM "xmltv.dtv">
<tv source-info-name="nobody,xmltv.net,nzxmltv.com">
    <channel id="693983e90c94b0607884273e-fr">
        <display-name>Manipulation : la voisine d'à côté</display-name>
        <icon src="https://images.pluto.tv/episodes/693983e90c94b0607884273e/screenshot16_9_1773407598126.jpg?fill=blur&amp;fit=fill&amp;fm=jpg&amp;h=540&amp;q=75&amp;w=960"/>
    </channel>
    <channel id="69836d61e090dedcb27c2839-fr">
        <display-name>Indignation</display-name>
        <icon src="https://images.pluto.tv/episodes/69836d61e090dedcb27c2839/screenshot16_9_1773407640117.jpg?fill=blur&amp;fit=fill&amp;fm=jpg&amp;h=540&amp;q=75&amp;w=960"/>
    </channel>
    <channel id="6980851f00cf117a55c8ca72-fr">
        <display-name>Nine</display-name>
        <icon src="https://images.pluto.tv/episodes/6980851f00cf117a55c8ca72/screenshot16_9_1770030368216.jpg?fill=blur&amp;fit=fill&amp;fm=jpg&amp;h=540&amp;q=75&amp;w=960"/>
    </channel>
    <channel id="68711e87a53444ef2accb3a0-fr">
        <display-name>Liberté Sauvage</display-name>
        <icon src="https://images.pluto.tv/episodes/68711e87a53444ef2accb3a0/screenshot16_9_1752243852206.jpg?fill=blur&amp;fit=fill&amp;fm=jpg&amp;h=540&amp;q=75&amp;w=960"/>
    </channel>
    <channel id="68711e81a53444ef2acbdfe7-fr">
        <display-name>Red Joan</display-name>
        <icon src="https://images.pluto.tv/episodes/68711e81a53444ef2acbdfe7/screenshot16_9_1752243843328.jpg?fill=blur&amp;fit=fill&amp;fm=jpg&amp;h=540&amp;q=75&amp;w=960"/>
    </channel>
    <channel id="612dfaf4dc29d20013b79abf-fr">
        <display-name>Absolution in love</display-name>
        <icon src="https://images.pluto.tv/episodes/612dfaf4dc29d20013b79abf/screenshot16_9.jpg?fill=blur&amp;fit=fill&amp;fm=jpg&amp;h=540&amp;q=75&amp;w=960"/>
    </channel>
    <channel id="6062dc2ba224c9001bb827ec-fr">
        <display-name>Aloha FR</display-name>
        <icon src="https://images.pluto.tv/episodes/6062dc2ba224c9001bb827ec/screenshot16_9.jpg?fill=blur&amp;fit=fill&amp;fm=jpg&amp;h=540&amp;q=75&amp;w=960"/>
    </channel>
    <channel id="68711e8fa53444ef2acdf992-fr">
        <display-name>Alana : Déesse de Justice</display-name>
        <icon src="https://images.pluto.tv/episodes/68711e8fa53444ef2acdf992/screenshot16_9_1768332963102.jpg?fill=blur&amp;fit=fill&amp;fm=jpg&amp;h=540&amp;q=75&amp;w=960"/>
    </channel>
    <channel id="6062fff5918e16001a4fbad5-fr">
        <display-name>Le droit du tuer?</display-name>
        <icon src="https://images.pluto.tv/episodes/6062fff5918e16001a4fbad5/screenshot16_9.jpg?fill=blur&amp;fit=fill&amp;fm=jpg&amp;h=540&amp;q=75&amp;w=960"/>
    </channel>
    <channel id="607002353bbc1b001aee2653-fr">
        <display-name>We love happy endings ! aka Not another Happy ending</display-name>
        <icon src="https://images.pluto.tv/episodes/607002353bbc1b001aee2653/screenshot16_9.jpg?fill=blur&amp;fit=fill&amp;fm=jpg&amp;h=540&amp;q=75&amp;w=960"/>
    </channel>
    <channel id="6901f0e369032f4edfddcb0e-fr">
        <display-name>The House Of The Spirits</display-name>
        <icon src="https://images.pluto.tv/episodes/6901f0e369032f4edfddcb0e/screenshot16_9_1761736088345.jpg?fill=blur&amp;fit=fill&amp;fm=jpg&amp;h=540&amp;q=75&amp;w=960"/>
    </channel>
    <channel id="6979f16200cf117a55424bbd-fr">
        <display-name>Ma Meilleure Amie</display-name>
        <icon src="https://images.pluto.tv/episodes/6979f16200cf117a55424bbd/screenshot16_9_1769599331733.jpg?fill=blur&amp;fit=fill&amp;fm=jpg&amp;h=540&amp;q=75&amp;w=960"/>
    </channel>
    <channel id="6943c3fef1f205fbbf9c5cd3-fr">
        <display-name>Happy Birthday</display-name>
        <icon src="https://images.pluto.tv/episodes/6943c3fef1f205fbbf9c5cd3/screenshot16_9_1766048769142.jpg?fill=blur&amp;fit=fill&amp;fm=jpg&amp;h=540&amp;q=75&amp;w=960"/>
    </channel>
    <channel id="6943c294b3298987989efe8c-fr">
        <display-name>Les Vies Privées De Pippa Lee</display-name>
        <icon src="https://images.pluto.tv/episodes/6943c294b3298987989efe8c/screenshot16_9_1766048406117.jpg?fill=blur&amp;fit=fill&amp;fm=jpg&amp;h=540&amp;q=75&amp;w=960"/>
    </channel>
    <channel id="68220e90a8cdcdbb7dea0339-fr">
        <display-name>My Happy Ending</display-name>
        <icon src="https://images.pluto.tv/episodes/68220e90a8cdcdbb7dea0339/screenshot16_9_1768333346732.jpg?fill=blur&amp;fit=fill&amp;fm=jpg&amp;h=540&amp;q=75&amp;w=960"/>
    </channel>
    <channel id="6980868facf7dd3dc4907d56-fr">
        <display-name>Joueurs</display-name>
        <icon src="https://images.pluto.tv/episodes/6980868facf7dd3dc4907d56/screenshot16_9_1770030736821.jpg?fill=blur&amp;fit=fill&amp;fm=jpg&amp;h=540&amp;q=75&amp;w=960"/>
    </channel>
    <channel id="67ac8369c13cf03484139a1f-fr">
        <display-name>Tous les chemins mènent à Rome</display-name>
        <icon src="https://images.pluto.tv/episodes/67ac8369c13cf03484139a1f/screenshot16_9.jpg?fill=blur&amp;fit=fill&amp;fm=jpg&amp;h=540&amp;q=75&amp;w=960"/>
    </channel>
    <channel id="68f5d8546fe1b6a13d6d92ef-fr">
        <display-name>10 ans déjà</display-name>
        <icon src="https://images.pluto.tv/episodes/68f5d8546fe1b6a13d6d92ef/screenshot16_9_1760942165552.jpg?fill=blur&amp;fit=fill&amp;fm=jpg&amp;h=540&amp;q=75&amp;w=960"/>
    </channel>
    <channel id="687117798eef10068fbd070b-fr">
        <display-name>Alone Together</display-name>
        <icon src="https://images.pluto.tv/episodes/687117798eef10068fbd070b/screenshot16_9_1768264600497.jpg?fill=blur&amp;fit=fill&amp;fm=jpg&amp;h=540&amp;q=75&amp;w=960"/>
    </channel>
    <channel id="6698baa99322c000136ce1e1-fr">
        <display-name>Un Secret Bien Gardé</display-name>
        <icon src="https://images.pluto.tv/episodes/6698baa99322c000136ce1e1/screenshot16_9_1768344481624.jpg?fill=blur&amp;fit=fill&amp;fm=jpg&amp;h=540&amp;q=75&amp;w=960"/>
    </channel>
    <channel id="65c49c561ffdb00013a1efe6-fr">
        <display-name>Camping, Love and Therapy</display-name>
        <icon src="https://images.pluto.tv/episodes/65c49c561ffdb00013a1efe6/screenshot16_9_1768433764452.jpg?fill=blur&amp;fit=fill&amp;fm=jpg&amp;h=540&amp;q=75&amp;w=960"/>
    </channel>
    <channel id="6698c04814c6d20013938ecf-fr">
        <display-name>Haute Couture</display-name>
        <icon src="https://images.pluto.tv/episodes/6698c04814c6d20013938ecf/screenshot16_9_1768344123711.jpg?fill=blur&amp;fit=fill&amp;fm=jpg&amp;h=540&amp;q=75&amp;w=960"/>
    </channel>
    <channel id="65c4a08fb65b870013f65aef-fr">
        <display-name>Ma belle-sœur bien aimée</display-name>
        <icon src="https://images.pluto.tv/episodes/65c4a08fb65b870013f65aef/screenshot16_9_1768472405451.jpg?fill=blur&amp;fit=fill&amp;fm=jpg&amp;h=540&amp;q=75&amp;w=960"/>
    </channel>
    <channel id="639198301fad0c0013d6dd3a-fr">
        <display-name>Une histoire de famille</display-name>
        <icon src="https://images.pluto.tv/episodes/639198301fad0c0013d6dd3a/screenshot16_9_1768264923736.jpg?fill=blur&amp;fit=fill&amp;fm=jpg&amp;h=540&amp;q=75&amp;w=960"/>
    </channel>
    <channel id="60196c875777bb001aaa19f5-fr">
        <display-name>Confession d'une adorable emmerdeuse</display-name>
        <icon src="https://images.pluto.tv/episodes/60196c875777bb001aaa19f5/screenshot16_9.jpg?fill=blur&amp;fit=fill&amp;fm=jpg&amp;h=540&amp;q=75&amp;w=960"/>
    </channel>
    <channel id="66c596202cb3a000136afe4e-fr">
        <display-name>New Year Blues</display-name>
        <icon src="https://images.pluto.tv/episodes/66c596202cb3a000136afe4e/screenshot16_9_1768443164434.jpg?fill=blur&amp;fit=fill&amp;fm=jpg&amp;h=540&amp;q=75&amp;w=960"/>
    </channel>
    <channel id="64df0a4db97a1e0013129811-fr">
        <display-name>The Escort</display-name>
        <icon src="https://images.pluto.tv/episodes/64df0a4db97a1e0013129811/screenshot16_9_1768439885059.jpg?fill=blur&amp;fit=fill&amp;fm=jpg&amp;h=540&amp;q=75&amp;w=960"/>
    </channel>
    <channel id="606d73c9a224c9001bb9473e-fr">
        <display-name>Elektra</display-name>
        <icon src="https://images.pluto.tv/episodes/606d73c9a224c9001bb9473e/screenshot16_9.jpg?fill=blur&amp;fit=fill&amp;fm=jpg&amp;h=540&amp;q=75&amp;w=960"/>
    </channel>
    <channel id="606eda885426cf001a3a8b9b-fr">
        <display-name>Ma super ex</display-name>
        <icon src="https://images.pluto.tv/episodes/606eda885426cf001a3a8b9b/screenshot16_9.jpg?fill=blur&amp;fit=fill&amp;fm=jpg&amp;h=540&amp;q=75&amp;w=960"/>
    </channel>
    <channel id="6984594271e7de966e5962c7-fr">
        <display-name>IP Man : Final Clash of Masters</display-name>
        <icon src="https://images.pluto.tv/episodes/6984594271e7de966e5962c7/screenshot16_9_1770281283004.jpg?fill=blur&amp;fit=fill&amp;fm=jpg&amp;h=540&amp;q=75&amp;w=960"/>
    </channel>
    <channel id="606eda7b5426cf001a3a8a87-fr">
        <display-name>Love, et autres drogues</display-name>
        <icon src="https://images.pluto.tv/episodes/606eda7b5426cf001a3a8a87/screenshot16_9.jpg?fill=blur&amp;fit=fill&amp;fm=jpg&amp;h=540&amp;q=75&amp;w=960"/>
    </channel>
    <channel id="695d031cdee1ecbcdd2de011-fr">
        <display-name>The Swordsman</display-name>
        <icon src="https://images.pluto.tv/episodes/695d031cdee1ecbcdd2de011/screenshot16_9_1767788007437.jpg?fill=blur&amp;fit=fill&amp;fm=jpg&amp;h=540&amp;q=75&amp;w=960"/>
    </channel>
    <channel id="695d16cf287ec44e140d356a-fr">
        <display-name>Sky Fire</display-name>
        <icon src="https://images.pluto.tv/episodes/695d16cf287ec44e140d356a/screenshot16_9_1768577014108.jpg?fill=blur&amp;fit=fill&amp;fm=jpg&amp;h=540&amp;q=75&amp;w=960"/>
    </channel>
    <channel id="698304f4e090dedcb243969d-fr">
        <display-name>Hungry Hearts</display-name>
        <icon src="https://images.pluto.tv/episodes/698304f4e090dedcb243969d/screenshot16_9_1770194165505.jpg?fill=blur&amp;fit=fill&amp;fm=jpg&amp;h=540&amp;q=75&amp;w=960"/>
    </channel>
    <channel id="6979f16600cf117a5542c1e6-fr">
        <display-name>Michael Clayton</display-name>
        <icon src="https://images.pluto.tv/episodes/6979f16600cf117a5542c1e6/screenshot16_9_1769599335037.jpg?fill=blur&amp;fit=fill&amp;fm=jpg&amp;h=540&amp;q=75&amp;w=960"/>
    </channel>
    <channel id="606eda835426cf001a3a8b13-fr">
        <display-name>Meet Dave FR</display-name>
        <icon src="https://images.pluto.tv/episodes/606eda835426cf001a3a8b13/screenshot16_9.jpg?fill=blur&amp;fit=fill&amp;fm=jpg&amp;h=540&amp;q=75&amp;w=960"/>
    </channel>
    <channel id="606d73b8a224c9001bb9468e-fr">
        <display-name>Sexy Movie</display-name>
        <icon src="https://images.pluto.tv/episodes/606d73b8a224c9001bb9468e/screenshot16_9.jpg?fill=blur&amp;fit=fill&amp;fm=jpg&amp;h=540&amp;q=75&amp;w=960"/>
    </channel>
    <channel id="6062dc36a224c9001bb828fe-fr">
        <display-name>JFK - Affaire non classée</display-name>
        <icon src="https://images.pluto.tv/episodes/6062dc36a224c9001bb828fe/screenshot16_9_1768350241778.jpg?fill=blur&amp;fit=fill&amp;fm=jpg&amp;h=540&amp;q=75&amp;w=960"/>
    </channel>
    <channel id="606d73a5a224c9001bb9459e-fr">
        <display-name>Le chevalier black</display-name>
        <icon src="https://images.pluto.tv/episodes/606d73a5a224c9001bb9459e/screenshot16_9.jpg?fill=blur&amp;fit=fill&amp;fm=jpg&amp;h=540&amp;q=75&amp;w=960"/>
    </channel>
    <channel id="69493159a7396485f8575afc-fr">
        <display-name>Captivity</display-name>
        <icon src="https://images.pluto.tv/episodes/69493159a7396485f8575afc/screenshot16_9_1766417959741.jpg?fill=blur&amp;fit=fill&amp;fm=jpg&amp;h=540&amp;q=75&amp;w=960"/>
    </channel>
    <channel id="695d031fdee1ecbcdd2e4203-fr">
        <display-name>Tireur D'elite</display-name>
        <icon src="https://images.pluto.tv/episodes/695d031fdee1ecbcdd2e4203/screenshot16_9_1767788291382.jpg?fill=blur&amp;fit=fill&amp;fm=jpg&amp;h=540&amp;q=75&amp;w=960"/>
    </channel>
    <channel id="68711d1e4f8d4a99171db17d-fr">
        <display-name>Kung Fu Killer</display-name>
        <icon src="https://images.pluto.tv/episodes/68711d1e4f8d4a99171db17d/screenshot16_9_1752293687858.jpg?fill=blur&amp;fit=fill&amp;fm=jpg&amp;h=540&amp;q=75&amp;w=960"/>
    </channel>
    <channel id="6389c7047756bf001300c6fa-fr">
        <display-name>Lady Bloodfight FR</display-name>
        <icon src="https://images.pluto.tv/episodes/6389c7047756bf001300c6fa/screenshot16_9_1768347366463.jpg?fill=blur&amp;fit=fill&amp;fm=jpg&amp;h=540&amp;q=75&amp;w=960"/>
    </channel>
    <channel id="69808681acf7dd3dc48e56ff-fr">
        <display-name>Un Anglais A New York</display-name>
        <icon src="https://images.pluto.tv/episodes/69808681acf7dd3dc48e56ff/screenshot16_9_1770030722688.jpg?fill=blur&amp;fit=fill&amp;fm=jpg&amp;h=540&amp;q=75&amp;w=960"/>
    </channel>
    <channel id="693834e58e21e6575ad5f41f-fr">
        <display-name>Breakwater</display-name>
        <icon src="https://images.pluto.tv/episodes/693834e58e21e6575ad5f41f/screenshot16_9_1765291239287.jpg?fill=blur&amp;fit=fill&amp;fm=jpg&amp;h=540&amp;q=75&amp;w=960"/>
    </channel>
    <channel id="606ec693726ca7001a8fea38-fr">
        <display-name>Black/White</display-name>
        <icon src="https://images.pluto.tv/episodes/606ec693726ca7001a8fea38/screenshot16_9_1768413962345.jpg?fill=blur&amp;fit=fill&amp;fm=jpg&amp;h=540&amp;q=75&amp;w=960"/>
    </channel>
    <channel id="68ad51999889a990ed143273-fr">
        <display-name>RBG</display-name>
        <icon src="https://images.pluto.tv/episodes/68ad51999889a990ed143273/screenshot16_9_1756199287761.jpg?fill=blur&amp;fit=fill&amp;fm=jpg&amp;h=540&amp;q=75&amp;w=960"/>
    </channel>
    <channel id="67ac84d8a2d5a665faa93d3a-fr">
        <display-name>La Bataille des Sexes</display-name>
        <icon src="https://images.pluto.tv/episodes/67ac84d8a2d5a665faa93d3a/screenshot16_9_1768424041928.jpg?fill=blur&amp;fit=fill&amp;fm=jpg&amp;h=540&amp;q=75&amp;w=960"/>
    </channel>
    <channel id="6964afa1c1938362f30d4030-fr">
        <display-name>The Great Battle</display-name>
        <icon src="https://images.pluto.tv/episodes/6964afa1c1938362f30d4030/screenshot16_9_1768206339343.jpg?fill=blur&amp;fit=fill&amp;fm=jpg&amp;h=540&amp;q=75&amp;w=960"/>
    </channel>
    <channel id="6983038acd24a9501ec86de2-fr">
        <display-name>The Happy Prince</display-name>
        <icon src="https://images.pluto.tv/episodes/6983038acd24a9501ec86de2/screenshot16_9_1770193803838.jpg?fill=blur&amp;fit=fill&amp;fm=jpg&amp;h=540&amp;q=75&amp;w=960"/>
    </channel>
    <channel id="6980868aacf7dd3dc48fa53f-fr">
        <display-name>Every Thing Will Be Fine</display-name>
        <icon src="https://images.pluto.tv/episodes/6980868aacf7dd3dc48fa53f/screenshot16_9_1770030731404.jpg?fill=blur&amp;fit=fill&amp;fm=jpg&amp;h=540&amp;q=75&amp;w=960"/>
    </channel>
    <channel id="69832112aa2e528402f154c4-fr">
        <display-name>Kids In Love</display-name>
        <icon src="https://images.pluto.tv/episodes/69832112aa2e528402f154c4/screenshot16_9_1770201363025.jpg?fill=blur&amp;fit=fill&amp;fm=jpg&amp;h=540&amp;q=75&amp;w=960"/>
    </channel>
    <channel id="698083b1e090dedcb2e92f7b-fr">
        <display-name>D'artagnan</display-name>
        <icon src="https://images.pluto.tv/episodes/698083b1e090dedcb2e92f7b/screenshot16_9_1770030002502.jpg?fill=blur&amp;fit=fill&amp;fm=jpg&amp;h=540&amp;q=75&amp;w=960"/>
    </channel>
    <channel id="694142bc0c94b06078824f7c-fr">
        <display-name>Italian Race</display-name>
        <icon src="https://images.pluto.tv/episodes/694142bc0c94b06078824f7c/screenshot16_9_1765885086803.jpg?fill=blur&amp;fit=fill&amp;fm=jpg&amp;h=540&amp;q=75&amp;w=960"/>
    </channel>
    <channel id="6980851900cf117a55c80692-fr">
        <display-name>Peyrol Le Boucanier</display-name>
        <icon src="https://images.pluto.tv/episodes/6980851900cf117a55c80692/screenshot16_9_1770030362435.jpg?fill=blur&amp;fit=fill&amp;fm=jpg&amp;h=540&amp;q=75&amp;w=960"/>
    </channel>
    <channel id="6949261c849adb201eddd62d-fr">
        <display-name>Coma</display-name>
        <icon src="https://images.pluto.tv/episodes/6949261c849adb201eddd62d/screenshot16_9_1766401566095.jpg?fill=blur&amp;fit=fill&amp;fm=jpg&amp;h=540&amp;q=75&amp;w=960"/>
    </channel>
    <channel id="697a006cacf7dd3dc4267ceb-fr">
        <display-name>Et (beaucoup) plus si affinités</display-name>
        <icon src="https://images.pluto.tv/episodes/697a006cacf7dd3dc4267ceb/screenshot16_9_1769603182669.jpg?fill=blur&amp;fit=fill&amp;fm=jpg&amp;h=540&amp;q=75&amp;w=960"/>
    </channel>
    <channel id="6943c12c0c94b060781cd59d-fr">
        <display-name>3 Mariages De Trop</display-name>
        <icon src="https://images.pluto.tv/episodes/6943c12c0c94b060781cd59d/screenshot16_9_1766048045741.jpg?fill=blur&amp;fit=fill&amp;fm=jpg&amp;h=540&amp;q=75&amp;w=960"/>
    </channel>
    <channel id="6943c3fcf1f205fbbf9bfae1-fr">
        <display-name>Blackthorn</display-name>
        <icon src="https://images.pluto.tv/episodes/6943c3fcf1f205fbbf9bfae1/screenshot16_9_1766048765696.jpg?fill=blur&amp;fit=fill&amp;fm=jpg&amp;h=540&amp;q=75&amp;w=960"/>
    </channel>
    <channel id="6943c299b3298987989fd6a3-fr">
        <display-name>Hold Up</display-name>
        <icon src="https://images.pluto.tv/episodes/6943c299b3298987989fd6a3/screenshot16_9_1766048502861.jpg?fill=blur&amp;fit=fill&amp;fm=jpg&amp;h=540&amp;q=75&amp;w=960"/>
    </channel>
    <channel id="69493520f1f205fbbf968107-fr">
        <display-name>Beyond the Edge</display-name>
        <icon src="https://images.pluto.tv/episodes/69493520f1f205fbbf968107/screenshot16_9_1766406846364.jpg?fill=blur&amp;fit=fill&amp;fm=jpg&amp;h=540&amp;q=75&amp;w=960"/>
    </channel>
    <channel id="69397fb482bb361505547813-fr">
        <display-name>Ice Storm tempête Polaire</display-name>
        <icon src="https://images.pluto.tv/episodes/69397fb482bb361505547813/screenshot16_9_1765382717567.jpg?fill=blur&amp;fit=fill&amp;fm=jpg&amp;h=540&amp;q=75&amp;w=960"/>
    </channel>
    <channel id="69397fba82bb36150554da40-fr">
        <display-name>Top Gunner : Danger Zone</display-name>
        <icon src="https://images.pluto.tv/episodes/69397fba82bb36150554da40/screenshot16_9_1765429675908.jpg?fill=blur&amp;fit=fill&amp;fm=jpg&amp;h=540&amp;q=75&amp;w=960"/>
    </channel>
    <channel id="69397fbc82bb361505553c2e-fr">
        <display-name>Une idée de génie</display-name>
        <icon src="https://images.pluto.tv/episodes/69397fbc82bb361505553c2e/screenshot16_9_1765375933537.jpg?fill=blur&amp;fit=fill&amp;fm=jpg&amp;h=540&amp;q=75&amp;w=960"/>
    </channel>
    <channel id="693981196a2e5eeebc807350-fr">
        <display-name>Un Baiser pour Noël</display-name>
        <icon src="https://images.pluto.tv/episodes/693981196a2e5eeebc807350/screenshot16_9_1765385845754.jpg?fill=blur&amp;fit=fill&amp;fm=jpg&amp;h=540&amp;q=75&amp;w=960"/>
    </channel>
    <channel id="69398281a48fba0b7ed1babc-fr">
        <display-name>Last Survivors</display-name>
        <icon src="https://images.pluto.tv/episodes/69398281a48fba0b7ed1babc/screenshot16_9_1765378597239.jpg?fill=blur&amp;fit=fill&amp;fm=jpg&amp;h=540&amp;q=75&amp;w=960"/>
    </channel>
    <channel id="693983ed0c94b0607884eb1a-fr">
        <display-name>Un Héros pour Noël</display-name>
        <icon src="https://images.pluto.tv/episodes/693983ed0c94b0607884eb1a/screenshot16_9_1765386954007.jpg?fill=blur&amp;fit=fill&amp;fm=jpg&amp;h=540&amp;q=75&amp;w=960"/>
    </channel>
    <channel id="6943c296b3298987989f74b6-fr">
        <display-name>La Fiancée Des Neiges</display-name>
        <icon src="https://images.pluto.tv/episodes/6943c296b3298987989f74b6/screenshot16_9_1766053865389.jpg?fill=blur&amp;fit=fill&amp;fm=jpg&amp;h=540&amp;q=75&amp;w=960"/>
    </channel>
    <channel id="693a8c49843d41d24991e1cd-fr">
        <display-name>Storm Chasers</display-name>
        <icon src="https://images.pluto.tv/episodes/693a8c49843d41d24991e1cd/screenshot16_9_1765444683996.jpg?fill=blur&amp;fit=fill&amp;fm=jpg&amp;h=540&amp;q=75&amp;w=960"/>
    </channel>
    <channel id="69397b796a2e5eeebc7b1cbc-fr">
        <display-name>Top Gunner: America vs Russia</display-name>
        <icon src="https://images.pluto.tv/episodes/69397b796a2e5eeebc7b1cbc/screenshot16_9_1765379042955.jpg?fill=blur&amp;fit=fill&amp;fm=jpg&amp;h=540&amp;q=75&amp;w=960"/>
    </channel>
    <channel id="69382f9c0c94b06078119ab6-fr">
        <display-name>American Star</display-name>
        <icon src="https://images.pluto.tv/episodes/69382f9c0c94b06078119ab6/screenshot16_9_1765289885972.jpg?fill=blur&amp;fit=fill&amp;fm=jpg&amp;h=540&amp;q=75&amp;w=960"/>
    </channel>
    <channel id="69382f9e0c94b0607811fcc2-fr">
        <display-name>Attack on Titan</display-name>
        <icon src="https://images.pluto.tv/episodes/69382f9e0c94b0607811fcc2/screenshot16_9_1765289887856.jpg?fill=blur&amp;fit=fill&amp;fm=jpg&amp;h=540&amp;q=75&amp;w=960"/>
    </channel>
    <channel id="693834ee8e21e6575ad66937-fr">
        <display-name>Butcher's Crossing</display-name>
        <icon src="https://images.pluto.tv/episodes/693834ee8e21e6575ad66937/screenshot16_9_1765291248134.jpg?fill=blur&amp;fit=fill&amp;fm=jpg&amp;h=540&amp;q=75&amp;w=960"/>
    </channel>
    <channel id="69397475232b4e31aacff847-fr">
        <display-name>Coup de Foudre Mode d'Emploi</display-name>
        <icon src="https://images.pluto.tv/episodes/69397475232b4e31aacff847/screenshot16_9_1765429436996.jpg?fill=blur&amp;fit=fill&amp;fm=jpg&amp;h=540&amp;q=75&amp;w=960"/>
    </channel>
    <channel id="69397e49a48fba0b7ecc647b-fr">
        <display-name>Séduction Eternelle</display-name>
        <icon src="https://images.pluto.tv/episodes/69397e49a48fba0b7ecc647b/screenshot16_9_1765380014612.jpg?fill=blur&amp;fit=fill&amp;fm=jpg&amp;h=540&amp;q=75&amp;w=960"/>
    </channel>
    <channel id="690242733fb09016da4da24e-fr">
        <display-name>Blue Mountain State: The Rise of Thadlan</display-name>
        <icon src="https://images.pluto.tv/episodes/690242733fb09016da4da24e/screenshot16_9_1761762270889.jpg?fill=blur&amp;fit=fill&amp;fm=jpg&amp;h=540&amp;q=75&amp;w=960"/>
    </channel>
    <channel id="67ea393946d66c4aa09c0f41-fr">
        <display-name>Never Back Down</display-name>
        <icon src="https://images.pluto.tv/episodes/67ea393946d66c4aa09c0f41/screenshot16_9_1744964334039.jpg?fill=blur&amp;fit=fill&amp;fm=jpg&amp;h=540&amp;q=75&amp;w=960"/>
    </channel>
    <channel id="69271fd182bb361505ef90aa-fr">
        <display-name>The Deal</display-name>
        <icon src="https://images.pluto.tv/episodes/69271fd182bb361505ef90aa/screenshot16_9_1764228749153.jpg?fill=blur&amp;fit=fill&amp;fm=jpg&amp;h=540&amp;q=75&amp;w=960"/>
    </channel>
    <channel id="6871177c8eef10068fbd68fd-fr">
        <display-name>Andron</display-name>
        <icon src="https://images.pluto.tv/episodes/6871177c8eef10068fbd68fd/screenshot16_9_1768265643044.jpg?fill=blur&amp;fit=fill&amp;fm=jpg&amp;h=540&amp;q=75&amp;w=960"/>
    </channel>
    <channel id="68711e91a53444ef2ace6b5b-fr">
        <display-name>Suicide Tourist</display-name>
        <icon src="https://images.pluto.tv/episodes/68711e91a53444ef2ace6b5b/screenshot16_9_1752243860671.jpg?fill=blur&amp;fit=fill&amp;fm=jpg&amp;h=540&amp;q=75&amp;w=960"/>
    </channel>
    <channel id="68711ff44f8d4a9917218c21-fr">
        <display-name>Act of Honor</display-name>
        <icon src="https://images.pluto.tv/episodes/68711ff44f8d4a9917218c21/screenshot16_9_1752244262917.jpg?fill=blur&amp;fit=fill&amp;fm=jpg&amp;h=540&amp;q=75&amp;w=960"/>
    </channel>
    <channel id="68711fe94f8d4a99171fd3ef-fr">
        <display-name>The Jacket</display-name>
        <icon src="https://images.pluto.tv/episodes/68711fe94f8d4a99171fd3ef/screenshot16_9_1768332610742.jpg?fill=blur&amp;fit=fill&amp;fm=jpg&amp;h=540&amp;q=75&amp;w=960"/>
    </channel>
    <channel id="68f5d8516fe1b6a13d6d3102-fr">
        <display-name>L'illusion verte</display-name>
        <icon src="https://images.pluto.tv/episodes/68f5d8516fe1b6a13d6d3102/screenshot16_9_1761576665507.jpg?fill=blur&amp;fit=fill&amp;fm=jpg&amp;h=540&amp;q=75&amp;w=960"/>
    </channel>
    <channel id="5fbf615499839e0013e069d5-fr">
        <display-name>They Came Together</display-name>
        <icon src="https://images.pluto.tv/episodes/5fbf615499839e0013e069d5/screenshot16_9_1768267249156.jpg?fill=blur&amp;fit=fill&amp;fm=jpg&amp;h=540&amp;q=75&amp;w=960"/>
    </channel>
    <channel id="68711d194f8d4a99171cddcd-fr">
        <display-name>Two Warriors : le combat du siècle</display-name>
        <icon src="https://images.pluto.tv/episodes/68711d194f8d4a99171cddcd/screenshot16_9_1768332965074.jpg?fill=blur&amp;fit=fill&amp;fm=jpg&amp;h=540&amp;q=75&amp;w=960"/>
    </channel>
    <channel id="68ad5037b76cf0ad37f781fd-fr">
        <display-name>L'Affaire Monet</display-name>
        <icon src="https://images.pluto.tv/episodes/68ad5037b76cf0ad37f781fd/screenshot16_9_1758874526583.jpg?fill=blur&amp;fit=fill&amp;fm=jpg&amp;h=540&amp;q=75&amp;w=960"/>
    </channel>
    <channel id="68711d1c4f8d4a99171d4f8e-fr">
        <display-name>Jane</display-name>
        <icon src="https://images.pluto.tv/episodes/68711d1c4f8d4a99171d4f8e/screenshot16_9_1768332963227.jpg?fill=blur&amp;fit=fill&amp;fm=jpg&amp;h=540&amp;q=75&amp;w=960"/>
    </channel>
    <channel id="6871177f8eef10068fbddb38-fr">
        <display-name>Burn</display-name>
        <icon src="https://images.pluto.tv/episodes/6871177f8eef10068fbddb38/screenshot16_9_1768265643414.jpg?fill=blur&amp;fit=fill&amp;fm=jpg&amp;h=540&amp;q=75&amp;w=960"/>
    </channel>
    <channel id="68ad5031b76cf0ad37f69d9b-fr">
        <display-name>2040</display-name>
        <icon src="https://images.pluto.tv/episodes/68ad5031b76cf0ad37f69d9b/screenshot16_9_1768422965282.jpg?fill=blur&amp;fit=fill&amp;fm=jpg&amp;h=540&amp;q=75&amp;w=960"/>
    </channel>
    <channel id="68936b5199a2f3e74a0f58a1-fr">
        <display-name>Party Girl</display-name>
        <icon src="https://images.pluto.tv/episodes/68936b5199a2f3e74a0f58a1/screenshot16_9_1768346785913.jpg?fill=blur&amp;fit=fill&amp;fm=jpg&amp;h=540&amp;q=75&amp;w=960"/>
    </channel>
    <channel id="68944d89cb15389834479443-fr">
        <display-name>Sprinter</display-name>
        <icon src="https://images.pluto.tv/episodes/68944d89cb15389834479443/screenshot16_9_1768331890429.jpg?fill=blur&amp;fit=fill&amp;fm=jpg&amp;h=540&amp;q=75&amp;w=960"/>
    </channel>
    <channel id="68944d8ccb1538983447f634-fr">
        <display-name>Les arnaqueurs</display-name>
        <icon src="https://images.pluto.tv/episodes/68944d8ccb1538983447f634/screenshot16_9_1768337999892.jpg?fill=blur&amp;fit=fill&amp;fm=jpg&amp;h=540&amp;q=75&amp;w=960"/>
    </channel>
    <channel id="68944d93cb1538983448ca9d-fr">
        <display-name>MVP</display-name>
        <icon src="https://images.pluto.tv/episodes/68944d93cb1538983448ca9d/screenshot16_9_1754549654041.jpg?fill=blur&amp;fit=fill&amp;fm=jpg&amp;h=540&amp;q=75&amp;w=960"/>
    </channel>
    <channel id="68944c32cb15389834473242-fr">
        <display-name>The Short History of the Long Road</display-name>
        <icon src="https://images.pluto.tv/episodes/68944c32cb15389834473242/screenshot16_9_1754549362390.jpg?fill=blur&amp;fit=fill&amp;fm=jpg&amp;h=540&amp;q=75&amp;w=960"/>
    </channel>
    <channel id="68936ca6fd92ab53e88171c4-fr">
        <display-name>Inuit</display-name>
        <icon src="https://images.pluto.tv/episodes/68936ca6fd92ab53e88171c4/screenshot16_9_1754492072156.jpg?fill=blur&amp;fit=fill&amp;fm=jpg&amp;h=540&amp;q=75&amp;w=960"/>
    </channel>
    <channel id="6895f201baa646038d362302-fr">
        <display-name>Jean de la Fontaine, le défi</display-name>
        <icon src="https://images.pluto.tv/episodes/6895f201baa646038d362302/screenshot16_9_1754657282800.jpg?fill=blur&amp;fit=fill&amp;fm=jpg&amp;h=540&amp;q=75&amp;w=960"/>
    </channel>
    <channel id="68944d96cb15389834492c8e-fr">
        <display-name>Voltaire et l'affaire Calas</display-name>
        <icon src="https://images.pluto.tv/episodes/68944d96cb15389834492c8e/screenshot16_9_1754549656251.jpg?fill=blur&amp;fit=fill&amp;fm=jpg&amp;h=540&amp;q=75&amp;w=960"/>
    </channel>
    <channel id="68944d99cb15389834499f07-fr">
        <display-name>Frères de sang</display-name>
        <icon src="https://images.pluto.tv/episodes/68944d99cb15389834499f07/screenshot16_9_1754549670718.jpg?fill=blur&amp;fit=fill&amp;fm=jpg&amp;h=540&amp;q=75&amp;w=960"/>
    </channel>
    <channel id="68936ca0fd92ab53e8809de9-fr">
        <display-name>Une place parmi les vivants</display-name>
        <icon src="https://images.pluto.tv/episodes/68936ca0fd92ab53e8809de9/screenshot16_9_1754492066962.jpg?fill=blur&amp;fit=fill&amp;fm=jpg&amp;h=540&amp;q=75&amp;w=960"/>
    </channel>
    <channel id="686b6f0931b6562298c1e843-fr">
        <display-name>Une Star Dans Ma Vie</display-name>
        <icon src="https://images.pluto.tv/episodes/686b6f0931b6562298c1e843/screenshot16_9_1751871244698.jpg?fill=blur&amp;fit=fill&amp;fm=jpg&amp;h=540&amp;q=75&amp;w=960"/>
    </channel>
    <programme channel="693983e90c94b0607884273e-fr" start="20260312212404 +0000" stop="20260314212404 +0000">
        <title>Manipulation : la voisine d'à côté</title>
        <desc>Alors que Doug a une liaison avec Lena, la jeune femme qui a loué la maison voisine de la sienne pour l'été, la mort suspecte du mari de cette dernière révèle l'existence d'une assurance vie conséquente.</desc>
        <icon src="https://images.pluto.tv/episodes/693983e90c94b0607884273e/screenshot16_9_1773407598126.jpg?fill=blur&amp;fit=fill&amp;fm=jpg&amp;h=540&amp;q=75&amp;w=960"/>
    </programme>
    <programme channel="69836d61e090dedcb27c2839-fr" start="20260312212404 +0000" stop="20260314212404 +0000">
        <title>Indignation</title>
        <desc>En 1951, Marcus quitte son New Jersey natal pour aller étudier dans une université conservatrice de l'Ohio, où il fait face à la répression sexuelle et l'antisémitisme.</desc>
        <icon src="https://images.pluto.tv/episodes/69836d61e090dedcb27c2839/screenshot16_9_1773407640117.jpg?fill=blur&amp;fit=fill&amp;fm=jpg&amp;h=540&amp;q=75&amp;w=960"/>
    </programme>
    <programme channel="6980851f00cf117a55c8ca72-fr" start="20260312212404 +0000" stop="20260314212404 +0000">
        <title>Nine</title>
        <desc>Le célèbre réalisateur Guido Contini lutte pour trouver l'équilibre dans sa vie professionnelle et personnelle, alors qu'il s'engage dans des relations dramatiques avec sa femme, sa maîtresse, sa muse, son agent et sa mère.</desc>
        <icon src="https://images.pluto.tv/episodes/6980851f00cf117a55c8ca72/screenshot16_9_1770030368216.jpg?fill=blur&amp;fit=fill&amp;fm=jpg&amp;h=540&amp;q=75&amp;w=960"/>
    </programme>
    <programme channel="68711e87a53444ef2accb3a0-fr" start="20260312212404 +0000" stop="20260314212404 +0000">
        <title>Liberté Sauvage</title>
        <desc>Stella, veuve, est propriétaire d'un ranch qu'elle tente de tenir à flots en faisant appel à des prisonniers qui l'aident à s'occuper de chevaux sauvages. Elle doit faire face à de menaçants bureaucrates qui veulent mettre fin au programme qu'elle anime.</desc>
        <icon src="https://images.pluto.tv/episodes/68711e87a53444ef2accb3a0/screenshot16_9_1752243852206.jpg?fill=blur&amp;fit=fill&amp;fm=jpg&amp;h=540&amp;q=75&amp;w=960"/>
    </programme>
    <programme channel="68711e81a53444ef2acbdfe7-fr" start="20260312212404 +0000" stop="20260314212404 +0000">
        <title>Red Joan</title>
        <desc>Red Joan relate l’histoire de Joan Stanley, accusée d’espionnage pour le KGB et d’avoir livré des secrets de fabrication de l’arme nucléaire à l’URSS.</desc>
        <icon src="https://images.pluto.tv/episodes/68711e81a53444ef2acbdfe7/screenshot16_9_1752243843328.jpg?fill=blur&amp;fit=fill&amp;fm=jpg&amp;h=540&amp;q=75&amp;w=960"/>
    </programme>
    <programme channel="612dfaf4dc29d20013b79abf-fr" start="20260312212404 +0000" stop="20260314212404 +0000">
        <title>Absolution in love</title>
        <desc>Deux familles se retrouvent à l'occasion du retour de l'un des fils. Mais ces retrouvailles vont faire réapparaître de vieux fantômes...</desc>
        <icon src="https://images.pluto.tv/episodes/612dfaf4dc29d20013b79abf/screenshot16_9.jpg?fill=blur&amp;fit=fill&amp;fm=jpg&amp;h=540&amp;q=75&amp;w=960"/>
    </programme>
    <programme channel="6062dc2ba224c9001bb827ec-fr" start="20260312212404 +0000" stop="20260314212404 +0000">
        <title>Aloha FR</title>
        <desc>Un militaire de renom retourne sur les terres ou il a connu les plus grands succes de sa carriere. Alors qu'il renoue des liens avec un amour de jeunesse, il tombe contre toute attente sous le charme d'une militaire de l'Air Force qu'on lui a assigné.</desc>
        <icon src="https://images.pluto.tv/episodes/6062dc2ba224c9001bb827ec/screenshot16_9.jpg?fill=blur&amp;fit=fill&amp;fm=jpg&amp;h=540&amp;q=75&amp;w=960"/>
    </programme>
    <programme channel="68711e8fa53444ef2acdf992-fr" start="20260312212404 +0000" stop="20260314212404 +0000">
        <title>Alana : Déesse de Justice</title>
        <desc>Séparée de ses parents à la naissance, Alana grandit dans une société corrompue. Sujette à d’étranges colères, elle découvre qu’elle est la réincarnation de Sri Asih, déesse de justice. Ses pouvoirs vont bientôt changer le cours des choses.</desc>
        <icon src="https://images.pluto.tv/episodes/68711e8fa53444ef2acdf992/screenshot16_9_1768332963102.jpg?fill=blur&amp;fit=fill&amp;fm=jpg&amp;h=540&amp;q=75&amp;w=960"/>
    </programme>
    <programme channel="6062fff5918e16001a4fbad5-fr" start="20260312212404 +0000" stop="20260314212404 +0000">
        <title>Le droit du tuer?</title>
        <desc>Après le viol de sa fille de dix ans par deux Blancs qui se croient au dessus de la loi, le père se fait justice en abattant les deux violeurs.</desc>
        <icon src="https://images.pluto.tv/episodes/6062fff5918e16001a4fbad5/screenshot16_9.jpg?fill=blur&amp;fit=fill&amp;fm=jpg&amp;h=540&amp;q=75&amp;w=960"/>
    </programme>
    <programme channel="607002353bbc1b001aee2653-fr" start="20260312212404 +0000" stop="20260314212404 +0000">
        <title>We love happy endings ! aka Not another Happy ending</title>
        <desc>Une écrivain dont les romans dépressifs rencontrent un grand succès perd l'inspiration en même temps qu'elle vit le parfait bonheur. Refusant de renoncer à cette mine d'or, son éditeur décide de rendre sa vie misérable pour lui faire retrouver sa plume.</desc>
        <icon src="https://images.pluto.tv/episodes/607002353bbc1b001aee2653/screenshot16_9.jpg?fill=blur&amp;fit=fill&amp;fm=jpg&amp;h=540&amp;q=75&amp;w=960"/>
    </programme>
    <programme channel="6901f0e369032f4edfddcb0e-fr" start="20260312212404 +0000" stop="20260314212404 +0000">
        <title>The House Of The Spirits</title>
        <desc>La Maison aux Esprits est une saga familiale romantique retraçant trois générations de la famille Trueba. Au cœur de cette saga se trouve la relation passionnée entre Clara, une jeune femme dotée d'un don surnaturel, et son mari autoritaire, Esteban.</desc>
        <icon src="https://images.pluto.tv/episodes/6901f0e369032f4edfddcb0e/screenshot16_9_1761736088345.jpg?fill=blur&amp;fit=fill&amp;fm=jpg&amp;h=540&amp;q=75&amp;w=960"/>
    </programme>
    <programme channel="6979f16200cf117a55424bbd-fr" start="20260312212404 +0000" stop="20260314212404 +0000">
        <title>Ma Meilleure Amie</title>
        <desc>Milly et Jess sont deux meilleures amies inséparables depuis l’enfance. Alors que Milly se voit diagnostiquer une grave maladie, Jess tombe enceinte de son premier enfant…</desc>
        <icon src="https://images.pluto.tv/episodes/6979f16200cf117a55424bbd/screenshot16_9_1769599331733.jpg?fill=blur&amp;fit=fill&amp;fm=jpg&amp;h=540&amp;q=75&amp;w=960"/>
    </programme>
    <programme channel="6943c3fef1f205fbbf9c5cd3-fr" start="20260312212404 +0000" stop="20260314212404 +0000">
        <title>Happy Birthday</title>
        <desc>Senna Berges court après la réussite dans son métier de styliste et dans sa vie privée. Mais rien ne se passe vraiment comme elle le souhaiterait. Jusqu'au jour de son 46ème anniversaire où elle rencontre Adam, un avocat sexy et sophistiqué qui tente de lui ravir son coeur.</desc>
        <icon src="https://images.pluto.tv/episodes/6943c3fef1f205fbbf9c5cd3/screenshot16_9_1766048769142.jpg?fill=blur&amp;fit=fill&amp;fm=jpg&amp;h=540&amp;q=75&amp;w=960"/>
    </programme>
    <programme channel="6943c294b3298987989efe8c-fr" start="20260312212404 +0000" stop="20260314212404 +0000">
        <title>Les Vies Privées De Pippa Lee</title>
        <desc>Pippa Lee s'est construite une vie confortable dans une atmosphère feutrée. Elle est dévouée à son mari plus âgé, ainsi qu'à ses enfants déjà adultes. Mais à l'approche de la cinquantaine, cette sérénité en apparence parfaite s'effrite. Pippa a connu une enfance tumultueuse et délurée où se sont mêlés sexe, drogue et rock'n'roll. Désormais, elle doit donc trouver un équilibre entre sa jeunesse troublée et « la femme trop rangée » qu'elle est devenue. Sa rencontre avec un mystérieux jeune homme va lui permet de trouver un nouveau sens à sa vie...</desc>
        <icon src="https://images.pluto.tv/episodes/6943c294b3298987989efe8c/screenshot16_9_1766048406117.jpg?fill=blur&amp;fit=fill&amp;fm=jpg&amp;h=540&amp;q=75&amp;w=960"/>
    </programme>
    <programme channel="68220e90a8cdcdbb7dea0339-fr" start="20260312212404 +0000" stop="20260314212404 +0000">
        <title>My Happy Ending</title>
        <desc>Lorsque Julia Roth, star hollywoodienne, découvre qu'elle est atteinte d'un cancer, elle décide de suivre une chimiothérapie incognito dans une petite clinique du Kent. Dans cette épreuve, Julia peut compter sur le soutien de trois autres patientes.</desc>
        <icon src="https://images.pluto.tv/episodes/68220e90a8cdcdbb7dea0339/screenshot16_9_1768333346732.jpg?fill=blur&amp;fit=fill&amp;fm=jpg&amp;h=540&amp;q=75&amp;w=960"/>
    </programme>
    <programme channel="6980868facf7dd3dc4907d56-fr" start="20260312212404 +0000" stop="20260314212404 +0000">
        <title>Joueurs</title>
        <desc>Lorsqu'Ella rencontre Abel, sa vie bascule. Dans le sillage de cet amant insaisissable, la jeune fille va découvrir le Paris cosmopolite et souterrain des cercles de jeux, où adrénaline et argent règnent. D’abord un pari, leur histoire se transforme en une passion dévorante.</desc>
        <icon src="https://images.pluto.tv/episodes/6980868facf7dd3dc4907d56/screenshot16_9_1770030736821.jpg?fill=blur&amp;fit=fill&amp;fm=jpg&amp;h=540&amp;q=75&amp;w=960"/>
    </programme>
    <programme channel="67ac8369c13cf03484139a1f-fr" start="20260312212404 +0000" stop="20260314212404 +0000">
        <title>Tous les chemins mènent à Rome</title>
        <desc>Une mère de famille un peu à cran, se voit partir en road trip en Italie avec son amour de jeunesse Italien, afin de rattraper sa fille rebelle, qui souhaite rejoindre New-York à tout prix.</desc>
        <icon src="https://images.pluto.tv/episodes/67ac8369c13cf03484139a1f/screenshot16_9.jpg?fill=blur&amp;fit=fill&amp;fm=jpg&amp;h=540&amp;q=75&amp;w=960"/>
    </programme>
    <programme channel="68f5d8546fe1b6a13d6d92ef-fr" start="20260312212404 +0000" stop="20260314212404 +0000">
        <title>10 ans déjà</title>
        <desc>10 ans après le diplôme, cinq amis se retrouvent lors d’une soirée de promotion. Entre rires, souvenirs et confidences, chacun fait le point sur sa vie et ses amours. Pour certains, c’est l’occasion de rallumer une flamme.</desc>
        <icon src="https://images.pluto.tv/episodes/68f5d8546fe1b6a13d6d92ef/screenshot16_9_1760942165552.jpg?fill=blur&amp;fit=fill&amp;fm=jpg&amp;h=540&amp;q=75&amp;w=960"/>
    </programme>
    <programme channel="687117798eef10068fbd070b-fr" start="20260312212404 +0000" stop="20260314212404 +0000">
        <title>Alone Together</title>
        <desc>June, critique culinaire, part en escapade dans le nord de l’État pour fuir la pandémie. Mais la chambre d’hôtes qu’elle a louée est déjà occupée par Charlie. Et quand son copain annule, elle réalise que le séjour pourrait durer plus que prévu…</desc>
        <icon src="https://images.pluto.tv/episodes/687117798eef10068fbd070b/screenshot16_9_1768264600497.jpg?fill=blur&amp;fit=fill&amp;fm=jpg&amp;h=540&amp;q=75&amp;w=960"/>
    </programme>
    <programme channel="6698baa99322c000136ce1e1-fr" start="20260312212404 +0000" stop="20260314212404 +0000">
        <title>Un Secret Bien Gardé</title>
        <desc>Prise de panique, une jeune femme avoue à un inconnu ses secrets les plus intimes car elle pense que l'avion dans lequel elle voyage est sur le point de s'écraser. Or, elle ignore que cet homme est son nouveau patron.</desc>
        <icon src="https://images.pluto.tv/episodes/6698baa99322c000136ce1e1/screenshot16_9_1768344481624.jpg?fill=blur&amp;fit=fill&amp;fm=jpg&amp;h=540&amp;q=75&amp;w=960"/>
    </programme>
    <programme channel="65c49c561ffdb00013a1efe6-fr" start="20260312212404 +0000" stop="20260314212404 +0000">
        <title>Camping, Love and Therapy</title>
        <desc>Pour sauver son mariage, Jack accepte une escapade amoureuse avec sa femme Amanda. Mais à leur arrivée, ils découvrent que l'endroit a été loué par un couple de hippies et à un beau gosse célibataire. Les vacances prennent vite une tournure inattendue.</desc>
        <icon src="https://images.pluto.tv/episodes/65c49c561ffdb00013a1efe6/screenshot16_9_1768433764452.jpg?fill=blur&amp;fit=fill&amp;fm=jpg&amp;h=540&amp;q=75&amp;w=960"/>
    </programme>
    <programme channel="6698c04814c6d20013938ecf-fr" start="20260312212404 +0000" stop="20260314212404 +0000">
        <title>Haute Couture</title>
        <desc>Tilly Dunnage, couturière talentueuse, décide, après de nombreuses années passées en Europe, de retourner dans sa ville natale en Australie pour assouvir sa soif de vengeance.</desc>
        <icon src="https://images.pluto.tv/episodes/6698c04814c6d20013938ecf/screenshot16_9_1768344123711.jpg?fill=blur&amp;fit=fill&amp;fm=jpg&amp;h=540&amp;q=75&amp;w=960"/>
    </programme>
    <programme channel="65c4a08fb65b870013f65aef-fr" start="20260312212404 +0000" stop="20260314212404 +0000">
        <title>Ma belle-sœur bien aimée</title>
        <desc>À l'occasion des 40 ans d'Audrey, son frère épouse une fille rencontrée en France. Les secrets sont révélés avant le mariage. Audrey et la jeune fiancée française ne s'entendent pas du tout !</desc>
        <icon src="https://images.pluto.tv/episodes/65c4a08fb65b870013f65aef/screenshot16_9_1768472405451.jpg?fill=blur&amp;fit=fill&amp;fm=jpg&amp;h=540&amp;q=75&amp;w=960"/>
    </programme>
    <programme channel="639198301fad0c0013d6dd3a-fr" start="20260312212404 +0000" stop="20260314212404 +0000">
        <title>Une histoire de famille</title>
        <desc>April, 39 ans, veut un bébé mais son mari la quitte. Lorsque sa mère adoptive meurt, elle est contactée par sa maman bio, animatrice d'une émission télévisée. April commence à voir le père divorcé de l'un de ses élèves à l'école.</desc>
        <icon src="https://images.pluto.tv/episodes/639198301fad0c0013d6dd3a/screenshot16_9_1768264923736.jpg?fill=blur&amp;fit=fill&amp;fm=jpg&amp;h=540&amp;q=75&amp;w=960"/>
    </programme>
    <programme channel="60196c875777bb001aaa19f5-fr" start="20260312212404 +0000" stop="20260314212404 +0000">
        <title>Confession d'une adorable emmerdeuse</title>
        <desc>Katya est une célibataire égocentrique et prête à tout pour réussir. Le jour, elle travaille dans une agence de publicité. La nuit, elle court les soirées branchées. Les choses se compliquent quand un inspecteur des impôts s’intéresse à son train de vie.</desc>
        <icon src="https://images.pluto.tv/episodes/60196c875777bb001aaa19f5/screenshot16_9.jpg?fill=blur&amp;fit=fill&amp;fm=jpg&amp;h=540&amp;q=75&amp;w=960"/>
    </programme>
    <programme channel="66c596202cb3a000136afe4e-fr" start="20260312212404 +0000" stop="20260314212404 +0000">
        <title>New Year Blues</title>
        <desc>Quatre couples très différents, avec des problèmes, des besoins et des préoccupations très différents, font face à leurs soucis et à leurs obstacles au début d'une nouvelle année. Ji Ho est un inspecteur de police divorcé de l'unité des crimes violents.</desc>
        <icon src="https://images.pluto.tv/episodes/66c596202cb3a000136afe4e/screenshot16_9_1768443164434.jpg?fill=blur&amp;fit=fill&amp;fm=jpg&amp;h=540&amp;q=75&amp;w=960"/>
    </programme>
    <programme channel="64df0a4db97a1e0013129811-fr" start="20260312212404 +0000" stop="20260314212404 +0000">
        <title>The Escort</title>
        <desc>Prêt à tout pour trouver un sujet d’article intéressant, un journaliste suit une prostituée diplômée de Stanford et s’introduit dans le monde des escorts girls de luxe.</desc>
        <icon src="https://images.pluto.tv/episodes/64df0a4db97a1e0013129811/screenshot16_9_1768439885059.jpg?fill=blur&amp;fit=fill&amp;fm=jpg&amp;h=540&amp;q=75&amp;w=960"/>
    </programme>
    <programme channel="606d73c9a224c9001bb9473e-fr" start="20260312212404 +0000" stop="20260314212404 +0000">
        <title>Elektra</title>
        <desc>Elektra, célèbre tueuse à gages, accepte un contrat qu’elle refusera plus tard de remplir en protégeant sa cible et la fille de celui-ci de la terrible et maléfique organisation criminelle appelée « La Main ».</desc>
        <icon src="https://images.pluto.tv/episodes/606d73c9a224c9001bb9473e/screenshot16_9.jpg?fill=blur&amp;fit=fill&amp;fm=jpg&amp;h=540&amp;q=75&amp;w=960"/>
    </programme>
    <programme channel="606eda885426cf001a3a8b9b-fr" start="20260312212404 +0000" stop="20260314212404 +0000">
        <title>Ma super ex</title>
        <desc>Un homme plaque sa petite amie de longue date et découvre que c’est une super-héroïne. Et elle veut se venger.</desc>
        <icon src="https://images.pluto.tv/episodes/606eda885426cf001a3a8b9b/screenshot16_9.jpg?fill=blur&amp;fit=fill&amp;fm=jpg&amp;h=540&amp;q=75&amp;w=960"/>
    </programme>
    <programme channel="6984594271e7de966e5962c7-fr" start="20260312212404 +0000" stop="20260314212404 +0000">
        <title>IP Man : Final Clash of Masters</title>
        <desc>En 1950 à Hong Kong, le maître de Wing Chun Ye Wen (Tang Wenlong) se fait remarquer et attire l'attention de Zheng Delong (Lin Fengyi). Il se retrouve alors confronté aux "4 Rois", des maîtres redoutables dans un univers de rivalités et de trahisons.</desc>
        <icon src="https://images.pluto.tv/episodes/6984594271e7de966e5962c7/screenshot16_9_1770281283004.jpg?fill=blur&amp;fit=fill&amp;fm=jpg&amp;h=540&amp;q=75&amp;w=960"/>
    </programme>
    <programme channel="606eda7b5426cf001a3a8a87-fr" start="20260312212404 +0000" stop="20260314212404 +0000">
        <title>Love, et autres drogues</title>
        <desc>Un commercial de Viagra à qui aucune femme ne résiste tombe amoureux d’une femme très indépendante.</desc>
        <icon src="https://images.pluto.tv/episodes/606eda7b5426cf001a3a8a87/screenshot16_9.jpg?fill=blur&amp;fit=fill&amp;fm=jpg&amp;h=540&amp;q=75&amp;w=960"/>
    </programme>
    <programme channel="695d031cdee1ecbcdd2de011-fr" start="20260312212404 +0000" stop="20260314212404 +0000">
        <title>The Swordsman</title>
        <desc>Corée, 1623. Afin de sauver sa fille Tae-ok, enlevée par des marchands d'esclaves à la solde des nouveaux Maîtres chinois Qing, Tae Yul, ancien guerrier émérite de la dynastie Joseon pour la défense de laquelle il a perdu l'usage d'un oeil, doit reprendre l'épée qu'il avait abandonnée après la chute du roi Gwanghaegun. Rattrapé par ses blessures et les démons de son passé, il devra combattre et vaincre rivaux et ennemis pour l'honneur des guerriers coréens et la vie de sa fille.</desc>
        <icon src="https://images.pluto.tv/episodes/695d031cdee1ecbcdd2de011/screenshot16_9_1767788007437.jpg?fill=blur&amp;fit=fill&amp;fm=jpg&amp;h=540&amp;q=75&amp;w=960"/>
    </programme>
    <programme channel="695d16cf287ec44e140d356a-fr" start="20260312212404 +0000" stop="20260314212404 +0000">
        <title>Sky Fire</title>
        <desc>Sur l'île paradisiaque de Tianhuov, la fête bat son plein, quand le volcan situé sur la fameuse ceinture volcanique du Pacifique, "L'Anneau de Feu", se réveille. Un jeune scientifique doit convaincre le propriétaire du site touristique d'évacuer le parc à thème avant qu'il ne soit trop tard...</desc>
        <icon src="https://images.pluto.tv/episodes/695d16cf287ec44e140d356a/screenshot16_9_1768577014108.jpg?fill=blur&amp;fit=fill&amp;fm=jpg&amp;h=540&amp;q=75&amp;w=960"/>
    </programme>
    <programme channel="698304f4e090dedcb243969d-fr" start="20260312212404 +0000" stop="20260314212404 +0000">
        <title>Hungry Hearts</title>
        <desc>Jude est Américain, Mina Italienne. Ils se rencontrent à New York, tombent fous amoureux et se marient. Lorsque Mina tombe enceinte, une nouvelle vie s’offre à eux. Mais l’arrivée du bébé bouleverse leur relation. Mina, persuadée que son enfant est unique, le protège de façon obsessionnelle du monde extérieur. Jude, par amour, respecte sa position jusqu’à ce qu’il comprenne que Mina commence à perdre contact avec la réalité.</desc>
        <icon src="https://images.pluto.tv/episodes/698304f4e090dedcb243969d/screenshot16_9_1770194165505.jpg?fill=blur&amp;fit=fill&amp;fm=jpg&amp;h=540&amp;q=75&amp;w=960"/>
    </programme>
    <programme channel="6979f16600cf117a5542c1e6-fr" start="20260312212404 +0000" stop="20260314212404 +0000">
        <title>Michael Clayton</title>
        <desc>Un cabinet juridique fait appel à son « magouilleur », après l'abandon d'un avocat représentant une société de produit chimique, coupable dans un recours collectif de plusieurs milliards de dollars.</desc>
        <icon src="https://images.pluto.tv/episodes/6979f16600cf117a5542c1e6/screenshot16_9_1769599335037.jpg?fill=blur&amp;fit=fill&amp;fm=jpg&amp;h=540&amp;q=75&amp;w=960"/>
    </programme>
    <programme channel="606eda835426cf001a3a8b13-fr" start="20260312212404 +0000" stop="20260314212404 +0000">
        <title>Meet Dave FR</title>
        <desc>Cherchant à sauver leur monde d’un destin tragique, un équipage d’extraterrestres minuscules qui ressemblent à des humains, arrive sur Terre dans le déguisement parfait : un vaisseau spatial en forme d’homme ordinaire.</desc>
        <icon src="https://images.pluto.tv/episodes/606eda835426cf001a3a8b13/screenshot16_9.jpg?fill=blur&amp;fit=fill&amp;fm=jpg&amp;h=540&amp;q=75&amp;w=960"/>
    </programme>
    <programme channel="606d73b8a224c9001bb9468e-fr" start="20260312212404 +0000" stop="20260314212404 +0000">
        <title>Sexy Movie</title>
        <desc>Les esprits tordus des auteurs de Scary Movie s’attaquent à la comédie romantique dans « Sexy Movie », un film pour ceux qui aiment les comédies romantiques ; et pour ceux qui les détestent.</desc>
        <icon src="https://images.pluto.tv/episodes/606d73b8a224c9001bb9468e/screenshot16_9.jpg?fill=blur&amp;fit=fill&amp;fm=jpg&amp;h=540&amp;q=75&amp;w=960"/>
    </programme>
    <programme channel="6062dc36a224c9001bb828fe-fr" start="20260312212404 +0000" stop="20260314212404 +0000">
        <title>JFK - Affaire non classée</title>
        <desc>Obsédé par la recherche de réponses, un avocat risque sa famille, sa carrière et sa propre vie afin de trouver la vérité sur l'assassinat de JFK.</desc>
        <icon src="https://images.pluto.tv/episodes/6062dc36a224c9001bb828fe/screenshot16_9_1768350241778.jpg?fill=blur&amp;fit=fill&amp;fm=jpg&amp;h=540&amp;q=75&amp;w=960"/>
    </programme>
    <programme channel="606d73a5a224c9001bb9459e-fr" start="20260312212404 +0000" stop="20260314212404 +0000">
        <title>Le chevalier black</title>
        <desc>Un homme dynamique et blagueur de South Central L.A. voyage accidentellement dans le temps vers une Angleterre médiévale. Il se retrouve à la tête du renversement d’un roi maléfique et gagne le cœur d’une femme aux idées très modernes.</desc>
        <icon src="https://images.pluto.tv/episodes/606d73a5a224c9001bb9459e/screenshot16_9.jpg?fill=blur&amp;fit=fill&amp;fm=jpg&amp;h=540&amp;q=75&amp;w=960"/>
    </programme>
    <programme channel="69493159a7396485f8575afc-fr" start="20260312212404 +0000" stop="20260314212404 +0000">
        <title>Captivity</title>
        <desc>Lors d’une mission scientifique en solitaire sur Mars, une série d’incidents techniques oblige le vaisseau du cosmonaute Chapaev à se poser d’urgence. Seul et livré à lui-même dans l’immensité de l’espace, il va rencontrer quelque chose d’inexplicable qui changera sa vie à jamais. Prisonnier de la planète rouge et devenu par son incroyable périble une légende vivante sur terre, Chapaev échappera-t-il à son destin ?</desc>
        <icon src="https://images.pluto.tv/episodes/69493159a7396485f8575afc/screenshot16_9_1766417959741.jpg?fill=blur&amp;fit=fill&amp;fm=jpg&amp;h=540&amp;q=75&amp;w=960"/>
    </programme>
    <programme channel="695d031fdee1ecbcdd2e4203-fr" start="20260312212404 +0000" stop="20260314212404 +0000">
        <title>Tireur D'elite</title>
        <desc>1915. Suite au déclenchement de la Première Guerre Mondiale, les armées du Tsar et du Kaiser s'affrontent en Lettonie, alors possession de l'Empire russe. Arturs, jeune paysan de seize ans, s'engage dans les bataillons de tirailleurs lettons avec son père et son frère après que sa mère ait été tuée par les Allemands. Il va devoir affronter l'horreur de la guerre et du deuil, et vivre dans sa chair les tourments d'une nation prise en tenailles par les ambitions territoriales des deux grandes puissances rivales...</desc>
        <icon src="https://images.pluto.tv/episodes/695d031fdee1ecbcdd2e4203/screenshot16_9_1767788291382.jpg?fill=blur&amp;fit=fill&amp;fm=jpg&amp;h=540&amp;q=75&amp;w=960"/>
    </programme>
    <programme channel="68711d1e4f8d4a99171db17d-fr" start="20260312212404 +0000" stop="20260314212404 +0000">
        <title>Kung Fu Killer</title>
        <desc>Un tueur abat les plus grands maîtres d’arts martiaux et laisse derrière lui une arme nommée Moonshadow. Le détenu Hou Mo, expert en kung-fu, reconnaît sa technique et propose d’aider la police à l’arrêter, en échange de sa liberté.</desc>
        <icon src="https://images.pluto.tv/episodes/68711d1e4f8d4a99171db17d/screenshot16_9_1752293687858.jpg?fill=blur&amp;fit=fill&amp;fm=jpg&amp;h=540&amp;q=75&amp;w=960"/>
    </programme>
    <programme channel="6389c7047756bf001300c6fa-fr" start="20260312212404 +0000" stop="20260314212404 +0000">
        <title>Lady Bloodfight FR</title>
        <desc>En arrivant à Hong Kong, une Américaine est battue et agressée par des voyous. Elle est prise en charge par un maître d'arts martiaux qui l'entraîne à une formidable compétition de combat connue sous le nom de Kumite.</desc>
        <icon src="https://images.pluto.tv/episodes/6389c7047756bf001300c6fa/screenshot16_9_1768347366463.jpg?fill=blur&amp;fit=fill&amp;fm=jpg&amp;h=540&amp;q=75&amp;w=960"/>
    </programme>
    <programme channel="69808681acf7dd3dc48e56ff-fr" start="20260312212404 +0000" stop="20260314212404 +0000">
        <title>Un Anglais A New York</title>
        <desc>Sidney Young, jeune écrivain ambitieux, veut devenir célèbre à tout prix. L'opportunité s'offre à lui lorsqu'il est engagé au sein du magazine "Sharps". Cependant, malgré ses tentatives pour s'adapter à ce milieu particulier, son côté arrogant et arriviste ne plaît pas à tout le monde. Malgré cela, il va s'obstiner à vouloir son quart d'heure de gloire.</desc>
        <icon src="https://images.pluto.tv/episodes/69808681acf7dd3dc48e56ff/screenshot16_9_1770030722688.jpg?fill=blur&amp;fit=fill&amp;fm=jpg&amp;h=540&amp;q=75&amp;w=960"/>
    </programme>
    <programme channel="693834e58e21e6575ad5f41f-fr" start="20260312212404 +0000" stop="20260314212404 +0000">
        <title>Breakwater</title>
        <desc>Un ex-détenu part à la recherche de la fille d'un ancien codétenu.</desc>
        <icon src="https://images.pluto.tv/episodes/693834e58e21e6575ad5f41f/screenshot16_9_1765291239287.jpg?fill=blur&amp;fit=fill&amp;fm=jpg&amp;h=540&amp;q=75&amp;w=960"/>
    </programme>
    <programme channel="606ec693726ca7001a8fea38-fr" start="20260312212404 +0000" stop="20260314212404 +0000">
        <title>Black/White</title>
        <desc>Un père sarcastique (Bernie Mac) a énormément de choses à raconter au sujet de sa fille qui souhaite épouser un jeune homme blanc (Ashton Kutcher).</desc>
        <icon src="https://images.pluto.tv/episodes/606ec693726ca7001a8fea38/screenshot16_9_1768413962345.jpg?fill=blur&amp;fit=fill&amp;fm=jpg&amp;h=540&amp;q=75&amp;w=960"/>
    </programme>
    <programme channel="68ad51999889a990ed143273-fr" start="20260312212404 +0000" stop="20260314212404 +0000">
        <title>RBG</title>
        <desc>Ce documentaire retrace le parcours de Ruth Bader Ginsburg, juge emblématique de la Cour suprême, pionnière de l’égalité femmes-hommes et figure de lutte contre les discriminations. Icône progressiste, elle fut un symbole fort face à l’ère Trump.</desc>
        <icon src="https://images.pluto.tv/episodes/68ad51999889a990ed143273/screenshot16_9_1756199287761.jpg?fill=blur&amp;fit=fill&amp;fm=jpg&amp;h=540&amp;q=75&amp;w=960"/>
    </programme>
    <programme channel="67ac84d8a2d5a665faa93d3a-fr" start="20260312212404 +0000" stop="20260314212404 +0000">
        <title>La Bataille des Sexes</title>
        <desc>Un regard sur les événements qui ont conduit au match de tennis de 1973 entre Bobby Riggs, champion masculin à la retraite, et Billie Jean King, gagnante du tournoi de Wimbledon.</desc>
        <icon src="https://images.pluto.tv/episodes/67ac84d8a2d5a665faa93d3a/screenshot16_9_1768424041928.jpg?fill=blur&amp;fit=fill&amp;fm=jpg&amp;h=540&amp;q=75&amp;w=960"/>
    </programme>
    <programme channel="6964afa1c1938362f30d4030-fr" start="20260312212404 +0000" stop="20260314212404 +0000">
        <title>The Great Battle</title>
        <desc>En l’an 645, l’Empereur Li, de la Dynastie Tang, envahit Goguryeo, l’un des anciens Royaumes de Corée. L’armée Tang enchaîne les victoires jusqu’à arriver à la forteresse d’Ansi, défendue par le Général Yang. Isolé, abandonné par le reste du Royaume, et largement dépassé en nombre par les centaines de milliers d’assaillants, Yang rassemble ses troupes, bien décidé à résister…</desc>
        <icon src="https://images.pluto.tv/episodes/6964afa1c1938362f30d4030/screenshot16_9_1768206339343.jpg?fill=blur&amp;fit=fill&amp;fm=jpg&amp;h=540&amp;q=75&amp;w=960"/>
    </programme>
    <programme channel="6983038acd24a9501ec86de2-fr" start="20260312212404 +0000" stop="20260314212404 +0000">
        <title>The Happy Prince</title>
        <desc>L'histoire inédite des derniers jours de la tragédie d'Oscar Wilde, une personne observant son propre échec avec une distance ironique et qui considère les difficultés qui assaillent sa vie avec détachement et humour.</desc>
        <icon src="https://images.pluto.tv/episodes/6983038acd24a9501ec86de2/screenshot16_9_1770193803838.jpg?fill=blur&amp;fit=fill&amp;fm=jpg&amp;h=540&amp;q=75&amp;w=960"/>
    </programme>
    <programme channel="6980868aacf7dd3dc48fa53f-fr" start="20260312212404 +0000" stop="20260314212404 +0000">
        <title>Every Thing Will Be Fine</title>
        <desc>Après une dispute avec sa compagne, Tomas, un jeune écrivain en mal d'inspiration, conduit sa voiture sans but sur une route enneigée. En raison de l'épaisse couche de neige et du manque de visibilité, Tomas percute mortellement un jeune garçon qui traversait la route. Après plusieurs années, et alors que ses relations volent en éclats et que tout semble perdu, Tomas trouve un chemin inattendu vers la rédemption: sa tragédie se transforme en succès littéraire.</desc>
        <icon src="https://images.pluto.tv/episodes/6980868aacf7dd3dc48fa53f/screenshot16_9_1770030731404.jpg?fill=blur&amp;fit=fill&amp;fm=jpg&amp;h=540&amp;q=75&amp;w=960"/>
    </programme>
    <programme channel="69832112aa2e528402f154c4-fr" start="20260312212404 +0000" stop="20260314212404 +0000">
        <title>Kids In Love</title>
        <desc>Refusant de suivre le chemin tout tracé par ses parents, Jack voit ses repères chamboulés lorsqu’il rencontre la belle Evelyn. À ses côtés, il va s’immerger dans l’univers des soirées sélectives de la scène londonienne, suivant ses nouveaux amis, dont la pétillante Viola. Dans ce quotidien tourbillonnant, de fêtes en festivals, à l’aube de l’âge adulte, Jack va devoir déterminer qui il est, et, surtout, qui il veut devenir.</desc>
        <icon src="https://images.pluto.tv/episodes/69832112aa2e528402f154c4/screenshot16_9_1770201363025.jpg?fill=blur&amp;fit=fill&amp;fm=jpg&amp;h=540&amp;q=75&amp;w=960"/>
    </programme>
    <programme channel="698083b1e090dedcb2e92f7b-fr" start="20260312212404 +0000" stop="20260314212404 +0000">
        <title>D'artagnan</title>
        <desc>Le roman d'Alexandre Dumas est mis à jour avec une influence orientale. D'Artagnan tente de rejoindre les gardes d'élite du roi, les mousquetaires royaux et de trouver le meurtrier de ses parents.</desc>
        <icon src="https://images.pluto.tv/episodes/698083b1e090dedcb2e92f7b/screenshot16_9_1770030002502.jpg?fill=blur&amp;fit=fill&amp;fm=jpg&amp;h=540&amp;q=75&amp;w=960"/>
    </programme>
    <programme channel="694142bc0c94b06078824f7c-fr" start="20260312212404 +0000" stop="20260314212404 +0000">
        <title>Italian Race</title>
        <desc>Giulia est une championne de course en puissance qui voit sa vie basculer lorsque son père décède. Mineure, elle ne peut compter que sur son frère qu'elle n'a pas vu depuis dix ans et qui est toxicomane. Ensemble, ils vont essayer de remonter la pente grâce à leur passion commune : la course automobile.</desc>
        <icon src="https://images.pluto.tv/episodes/694142bc0c94b06078824f7c/screenshot16_9_1765885086803.jpg?fill=blur&amp;fit=fill&amp;fm=jpg&amp;h=540&amp;q=75&amp;w=960"/>
    </programme>
    <programme channel="6980851900cf117a55c80692-fr" start="20260312212404 +0000" stop="20260314212404 +0000">
        <title>Peyrol Le Boucanier</title>
        <desc>Le boucanier Peyrol, porteur d'un message pour l'amiral de la flotte, force une fois de plus le blocus de la flotte anglaise au large de Toulon. Mais un commissaire du peuple, Dussard, l'accuse bientôt d'avoir dérobé un chargement d'or. Peyrol parvient à s'échapper et trouve refuge dans une ferme côtière isolée, où vivent Arlette, jeune femme instable, et sa tante Catherine.</desc>
        <icon src="https://images.pluto.tv/episodes/6980851900cf117a55c80692/screenshot16_9_1770030362435.jpg?fill=blur&amp;fit=fill&amp;fm=jpg&amp;h=540&amp;q=75&amp;w=960"/>
    </programme>
    <programme channel="6949261c849adb201eddd62d-fr" start="20260312212404 +0000" stop="20260314212404 +0000">
        <title>Coma</title>
        <desc>Suite à un terrible accident de voiture, Victor, un jeune et talentueux architecte, se retrouve immergé dans un monde étrange et inquiétant, fait des névroses et des souvenirs traumatisants de tous les patients plongés comme lui dans le coma. Dans cet au-delà chaotique et instable, où villes, monuments, rivières et objets semblent défier les lois de la physique, le danger est partout et l’horreur peut survenir à chaque instant. Alors qu’ils se battent pour leur survie, Victor et ses compagnons vont devoir découvrir qui manipule ces fragments de psychoses humaines pour se réveiller et trouver la sortie vers le monde réel.</desc>
        <icon src="https://images.pluto.tv/episodes/6949261c849adb201eddd62d/screenshot16_9_1766401566095.jpg?fill=blur&amp;fit=fill&amp;fm=jpg&amp;h=540&amp;q=75&amp;w=960"/>
    </programme>
    <programme channel="697a006cacf7dd3dc4267ceb-fr" start="20260312212404 +0000" stop="20260314212404 +0000">
        <title>Et (beaucoup) plus si affinités</title>
        <desc>Wallace a un coup de foudre pour son amie, Chantry, qui est en couple. Ensemble, ils vont découvrir ce que signifie être amoureux entre meilleurs amis.</desc>
        <icon src="https://images.pluto.tv/episodes/697a006cacf7dd3dc4267ceb/screenshot16_9_1769603182669.jpg?fill=blur&amp;fit=fill&amp;fm=jpg&amp;h=540&amp;q=75&amp;w=960"/>
    </programme>
    <programme channel="6943c12c0c94b060781cd59d-fr" start="20260312212404 +0000" stop="20260314212404 +0000">
        <title>3 Mariages De Trop</title>
        <desc>Ruth, une jeune biologiste à la vie sentimentale compliquée, est invitée coup sur coup aux mariages de trois de ses ex ! Dès le premier mariage, elle rencontre un charmant chirurgien esthétique, Tomas. Une nouvelle idylle commence. Un coup de théâtre remet tout en question lors du deuxième mariage…</desc>
        <icon src="https://images.pluto.tv/episodes/6943c12c0c94b060781cd59d/screenshot16_9_1766048045741.jpg?fill=blur&amp;fit=fill&amp;fm=jpg&amp;h=540&amp;q=75&amp;w=960"/>
    </programme>
    <programme channel="6943c3fcf1f205fbbf9bfae1-fr" start="20260312212404 +0000" stop="20260314212404 +0000">
        <title>Blackthorn</title>
        <desc>Passé pour mort depuis 1908, Butch Cassidy, le légendaire hors-la-loi, se cache en réalité en Bolivie depuis 20 ans sous le nom de James Blackthorn. Au crépuscule de sa vie, il n'aspire plus qu'à rentrer chez lui pour rencontrer ce fils qu'il n'a jamais connu. Lorsque sur sa route il croise un jeune ingénieur qui vient de braquer la mine dans laquelle il travaillait, Butch Cassidy démarre alors sa dernière chevauchée...</desc>
        <icon src="https://images.pluto.tv/episodes/6943c3fcf1f205fbbf9bfae1/screenshot16_9_1766048765696.jpg?fill=blur&amp;fit=fill&amp;fm=jpg&amp;h=540&amp;q=75&amp;w=960"/>
    </programme>
    <programme channel="6943c299b3298987989fd6a3-fr" start="20260312212404 +0000" stop="20260314212404 +0000">
        <title>Hold Up</title>
        <desc>Plusieurs braquages opérés par des gangs différents ont lieu simultanément dans la même banque. Un des otages tente de comprendre les raisons de cette troublante coïncidence. Mais en tombant sous le charme d'une guichetière aguicheuse, la tâche ne lui est pas facilitée...</desc>
        <icon src="https://images.pluto.tv/episodes/6943c299b3298987989fd6a3/screenshot16_9_1766048502861.jpg?fill=blur&amp;fit=fill&amp;fm=jpg&amp;h=540&amp;q=75&amp;w=960"/>
    </programme>
    <programme channel="69493520f1f205fbbf968107-fr" start="20260312212404 +0000" stop="20260314212404 +0000">
        <title>Beyond the Edge</title>
        <desc>Une bande d’arnaqueurs talentueux dotés de superpouvoirs tente de dévaliser un énorme casino, mais c’est sans compter sur un mystérieux rival qui semble tous les surpasser…</desc>
        <icon src="https://images.pluto.tv/episodes/69493520f1f205fbbf968107/screenshot16_9_1766406846364.jpg?fill=blur&amp;fit=fill&amp;fm=jpg&amp;h=540&amp;q=75&amp;w=960"/>
    </programme>
    <programme channel="69397fb482bb361505547813-fr" start="20260312212404 +0000" stop="20260314212404 +0000">
        <title>Ice Storm tempête Polaire</title>
        <desc>Lorsqu'une tempête hivernale dévastatrice s'abat, toute l'Amérique commence à geler.</desc>
        <icon src="https://images.pluto.tv/episodes/69397fb482bb361505547813/screenshot16_9_1765382717567.jpg?fill=blur&amp;fit=fill&amp;fm=jpg&amp;h=540&amp;q=75&amp;w=960"/>
    </programme>
    <programme channel="69397fba82bb36150554da40-fr" start="20260312212404 +0000" stop="20260314212404 +0000">
        <title>Top Gunner : Danger Zone</title>
        <desc>Des avions de chasse américains sont attaqués par un escadron de mystérieux avions de guerre et une bataille mortelle s'ensuit, menaçant la vie au-dessus et au-dessous de l'eau.</desc>
        <icon src="https://images.pluto.tv/episodes/69397fba82bb36150554da40/screenshot16_9_1765429675908.jpg?fill=blur&amp;fit=fill&amp;fm=jpg&amp;h=540&amp;q=75&amp;w=960"/>
    </programme>
    <programme channel="69397fbc82bb361505553c2e-fr" start="20260312212404 +0000" stop="20260314212404 +0000">
        <title>Une idée de génie</title>
        <desc>Deux amis s'associent et rencontrent le succès.</desc>
        <icon src="https://images.pluto.tv/episodes/69397fbc82bb361505553c2e/screenshot16_9_1765375933537.jpg?fill=blur&amp;fit=fill&amp;fm=jpg&amp;h=540&amp;q=75&amp;w=960"/>
    </programme>
    <programme channel="693981196a2e5eeebc807350-fr" start="20260312212404 +0000" stop="20260314212404 +0000">
        <title>Un Baiser pour Noël</title>
        <desc>Jennifer, une célèbre romancière, renoue avec sa famille et tombe sur son amour de jeunesse.</desc>
        <icon src="https://images.pluto.tv/episodes/693981196a2e5eeebc807350/screenshot16_9_1765385845754.jpg?fill=blur&amp;fit=fill&amp;fm=jpg&amp;h=540&amp;q=75&amp;w=960"/>
    </programme>
    <programme channel="69398281a48fba0b7ed1babc-fr" start="20260312212404 +0000" stop="20260314212404 +0000">
        <title>Last Survivors</title>
        <desc>un père et son fils vivent totalement isolés dans une forêt reculée depuis approximativement une vingtaine d'années.</desc>
        <icon src="https://images.pluto.tv/episodes/69398281a48fba0b7ed1babc/screenshot16_9_1765378597239.jpg?fill=blur&amp;fit=fill&amp;fm=jpg&amp;h=540&amp;q=75&amp;w=960"/>
    </programme>
    <programme channel="693983ed0c94b0607884eb1a-fr" start="20260312212404 +0000" stop="20260314212404 +0000">
        <title>Un Héros pour Noël</title>
        <desc>La veuve d'un héros de guerre recueille un soldat blessé qui vient de rentrer d'Afghanistan.</desc>
        <icon src="https://images.pluto.tv/episodes/693983ed0c94b0607884eb1a/screenshot16_9_1765386954007.jpg?fill=blur&amp;fit=fill&amp;fm=jpg&amp;h=540&amp;q=75&amp;w=960"/>
    </programme>
    <programme channel="6943c296b3298987989f74b6-fr" start="20260312212404 +0000" stop="20260314212404 +0000">
        <title>La Fiancée Des Neiges</title>
        <desc>Greta Kane est journaliste dans un magasine people. Pour obtenir une promotion, elle est chargée d'enquêter sur la famille Tannenhill afin de découvrir lequel des fils va se fiancer. Sur la route de Big Bear, lieu de vacances des Tannenhill, sa voiture reste coincée dans la neige. Elle tombe alors accidentellement sur Ben Tannenhill et se fait passer pour une autre personne. Lorsque Ben apprend que son ex-petite amie, Claire Sinclair, fréquente maintenant son frère et qu'il l'a amenée pour les vacances de Noël, il fait passer Greta pour sa petite amie. Greta profite de la situation pour pouvoir rester chez les Tannenhill et obtenir des informations. Mais au fur et à mesure, elle se sent de plus en plus à l'aise avec la famille et tombe amoureuse de Ben...</desc>
        <icon src="https://images.pluto.tv/episodes/6943c296b3298987989f74b6/screenshot16_9_1766053865389.jpg?fill=blur&amp;fit=fill&amp;fm=jpg&amp;h=540&amp;q=75&amp;w=960"/>
    </programme>
    <programme channel="693a8c49843d41d24991e1cd-fr" start="20260312212404 +0000" stop="20260314212404 +0000">
        <title>Storm Chasers</title>
        <desc>Amy, une ingénieur en quête de reconnaissance, est envoyée en Alaska pour vérifier l'affirmation d'un scientifique excentrique selon laquelle la capture de la foudre peut constituer une nouvelle source d'énergie renouvelable.</desc>
        <icon src="https://images.pluto.tv/episodes/693a8c49843d41d24991e1cd/screenshot16_9_1765444683996.jpg?fill=blur&amp;fit=fill&amp;fm=jpg&amp;h=540&amp;q=75&amp;w=960"/>
    </programme>
    <programme channel="69397b796a2e5eeebc7b1cbc-fr" start="20260312212404 +0000" stop="20260314212404 +0000">
        <title>Top Gunner: America vs Russia</title>
        <desc>Deux pilotes de chasse doivent arrêter une attaque russe.</desc>
        <icon src="https://images.pluto.tv/episodes/69397b796a2e5eeebc7b1cbc/screenshot16_9_1765379042955.jpg?fill=blur&amp;fit=fill&amp;fm=jpg&amp;h=540&amp;q=75&amp;w=960"/>
    </programme>
    <programme channel="69382f9c0c94b06078119ab6-fr" start="20260312212404 +0000" stop="20260314212404 +0000">
        <title>American Star</title>
        <desc>Un assassin en fin de mission arrive à Fuerteventura pour tuer un homme qu'il n'a jamais rencontré.</desc>
        <icon src="https://images.pluto.tv/episodes/69382f9c0c94b06078119ab6/screenshot16_9_1765289885972.jpg?fill=blur&amp;fit=fill&amp;fm=jpg&amp;h=540&amp;q=75&amp;w=960"/>
    </programme>
    <programme channel="69382f9e0c94b0607811fcc2-fr" start="20260312212404 +0000" stop="20260314212404 +0000">
        <title>Attack on Titan</title>
        <desc>Alors que l'eau viable s'épuise sur Terre, une mission est envoyée sur Titan.</desc>
        <icon src="https://images.pluto.tv/episodes/69382f9e0c94b0607811fcc2/screenshot16_9_1765289887856.jpg?fill=blur&amp;fit=fill&amp;fm=jpg&amp;h=540&amp;q=75&amp;w=960"/>
    </programme>
    <programme channel="693834ee8e21e6575ad66937-fr" start="20260312212404 +0000" stop="20260314212404 +0000">
        <title>Butcher's Crossing</title>
        <desc>Miller, chasseur de bisons, guide Will, un étudiant en quête d'aventure, dans une traque périlleuse.</desc>
        <icon src="https://images.pluto.tv/episodes/693834ee8e21e6575ad66937/screenshot16_9_1765291248134.jpg?fill=blur&amp;fit=fill&amp;fm=jpg&amp;h=540&amp;q=75&amp;w=960"/>
    </programme>
    <programme channel="69397475232b4e31aacff847-fr" start="20260312212404 +0000" stop="20260314212404 +0000">
        <title>Coup de Foudre Mode d'Emploi</title>
        <desc>Un écrivain rencontre par hasard l'amour de sa vie et découvre que la jeune femme est fiancée.</desc>
        <icon src="https://images.pluto.tv/episodes/69397475232b4e31aacff847/screenshot16_9_1765429436996.jpg?fill=blur&amp;fit=fill&amp;fm=jpg&amp;h=540&amp;q=75&amp;w=960"/>
    </programme>
    <programme channel="69397e49a48fba0b7ecc647b-fr" start="20260312212404 +0000" stop="20260314212404 +0000">
        <title>Séduction Eternelle</title>
        <desc>Alors qu'il est extrait du lieu de son accident de voiture, Michael doit trouver une compagne.</desc>
        <icon src="https://images.pluto.tv/episodes/69397e49a48fba0b7ecc647b/screenshot16_9_1765380014612.jpg?fill=blur&amp;fit=fill&amp;fm=jpg&amp;h=540&amp;q=75&amp;w=960"/>
    </programme>
    <programme channel="690242733fb09016da4da24e-fr" start="20260312212404 +0000" stop="20260314212404 +0000">
        <title>Blue Mountain State: The Rise of Thadlan</title>
        <desc>Thad ayant eu son diplôme et ayant été recruté à la NFL, c’est maintenant à Alex, le quarterback, de diriger son équipe mais aussi de se battre pour empêcher que le doyen vindicatif ne ferme définitivement sa maison.</desc>
        <icon src="https://images.pluto.tv/episodes/690242733fb09016da4da24e/screenshot16_9_1761762270889.jpg?fill=blur&amp;fit=fill&amp;fm=jpg&amp;h=540&amp;q=75&amp;w=960"/>
    </programme>
    <programme channel="67ea393946d66c4aa09c0f41-fr" start="20260312212404 +0000" stop="20260314212404 +0000">
        <title>Never Back Down</title>
        <desc>A bullied high school newcomer (Sean Faris) learns the fighting arts from a savvy mentor (Djimon Hounsou) and proves his mettle at underground mixed martial arts contests.</desc>
        <icon src="https://images.pluto.tv/episodes/67ea393946d66c4aa09c0f41/screenshot16_9_1744964334039.jpg?fill=blur&amp;fit=fill&amp;fm=jpg&amp;h=540&amp;q=75&amp;w=960"/>
    </programme>
    <programme channel="69271fd182bb361505ef90aa-fr" start="20260312212404 +0000" stop="20260314212404 +0000">
        <title>The Deal</title>
        <desc>Après qu'une pandémie sans précédent a ravagé l'humanité, une organisation totalitaire, le Bureau, a enfermé les survivants à l'intérieur d'une cité sans âme, où chaque individu est encouragé à signer le "Deal”. Acceptez-le et vous recevrez emploi, logement et soins médicaux pendant vingt ans. Après quoi, vous devrez mourir et laisser votre place.
Tala Bayani a accepté le Deal quand elle était enceinte et seule. Depuis, elle a tout fait pour que sa fille Analyn n'ait pas à faire le même choix. Quand, cinq jours seulement avant la mort programmée de sa mère, Analyn reçoit un diagnostic médical inattendu, Tala va devoir se battre dans le peu de temps qu'il lui reste pour que sa fille échappe à l'asservissement à vie imposé par Le Deal.</desc>
        <icon src="https://images.pluto.tv/episodes/69271fd182bb361505ef90aa/screenshot16_9_1764228749153.jpg?fill=blur&amp;fit=fill&amp;fm=jpg&amp;h=540&amp;q=75&amp;w=960"/>
    </programme>
    <programme channel="6871177c8eef10068fbd68fd-fr" start="20260312212404 +0000" stop="20260314212404 +0000">
        <title>Andron</title>
        <desc>Un groupe se réveille dans le labyrinthe sombre d’Andron, sans souvenir. Pour s’en sortir, ils doivent déchiffrer codes et signaux, et relever les défis mortels de ce lieu mystérieux.</desc>
        <icon src="https://images.pluto.tv/episodes/6871177c8eef10068fbd68fd/screenshot16_9_1768265643044.jpg?fill=blur&amp;fit=fill&amp;fm=jpg&amp;h=540&amp;q=75&amp;w=960"/>
    </programme>
    <programme channel="68711e91a53444ef2ace6b5b-fr" start="20260312212404 +0000" stop="20260314212404 +0000">
        <title>Suicide Tourist</title>
        <desc>Max, détective pour une assurance, apprend qu’il est condamné par une tumeur. Enquêtant sur un homme disparu, il arrive à l’hôtel Aurora, lieu isolé où l’on accompagne les suicides. Hanté par sa propre fin, il découvre un univers troublant.</desc>
        <icon src="https://images.pluto.tv/episodes/68711e91a53444ef2ace6b5b/screenshot16_9_1752243860671.jpg?fill=blur&amp;fit=fill&amp;fm=jpg&amp;h=540&amp;q=75&amp;w=960"/>
    </programme>
    <programme channel="68711ff44f8d4a9917218c21-fr" start="20260312212404 +0000" stop="20260314212404 +0000">
        <title>Act of Honor</title>
        <desc>Une unité rebelle connue sur le nom de « War Pigs » doit traverser les lignes ennemies pour exterminer des nazis et pour capturer une arme secrète d'Hitler par tous les moyens possibles...</desc>
        <icon src="https://images.pluto.tv/episodes/68711ff44f8d4a9917218c21/screenshot16_9_1752244262917.jpg?fill=blur&amp;fit=fill&amp;fm=jpg&amp;h=540&amp;q=75&amp;w=960"/>
    </programme>
    <programme channel="68711fe94f8d4a99171fd3ef-fr" start="20260312212404 +0000" stop="20260314212404 +0000">
        <title>The Jacket</title>
        <desc>Un soldat amnésique, accusé de meurtre, subit une étrange expérience à l’hôpital. Plongé dans une camisole, il voyage dans le temps, découvre son passé et un futur possible… Mais il ne lui reste que quatre jours pour changer le cours des choses.</desc>
        <icon src="https://images.pluto.tv/episodes/68711fe94f8d4a99171fd3ef/screenshot16_9_1768332610742.jpg?fill=blur&amp;fit=fill&amp;fm=jpg&amp;h=540&amp;q=75&amp;w=960"/>
    </programme>
    <programme channel="68f5d8516fe1b6a13d6d3102-fr" start="20260312212404 +0000" stop="20260314212404 +0000">
        <title>L'illusion verte</title>
        <desc>Les industriels veulent se créer une image plus respectable. En se procurant leurs produits bio ou éco-responsables, les consommateurs acheteraient vert. Mais tout cela ne serait que mensonge, du greenwashing ou éco-blanchiment…</desc>
        <icon src="https://images.pluto.tv/episodes/68f5d8516fe1b6a13d6d3102/screenshot16_9_1761576665507.jpg?fill=blur&amp;fit=fill&amp;fm=jpg&amp;h=540&amp;q=75&amp;w=960"/>
    </programme>
    <programme channel="5fbf615499839e0013e069d5-fr" start="20260312212404 +0000" stop="20260314212404 +0000">
        <title>They Came Together</title>
        <desc>Lorsque Joel et Molly  se rencontrent, c'est la haine à première vue : lui et sa grande corporation Candy Company menacent de fermer son magasin de bonbons indépendant et original à elle. De plus, Joel est obsédé par son ex sexy.</desc>
        <icon src="https://images.pluto.tv/episodes/5fbf615499839e0013e069d5/screenshot16_9_1768267249156.jpg?fill=blur&amp;fit=fill&amp;fm=jpg&amp;h=540&amp;q=75&amp;w=960"/>
    </programme>
    <programme channel="68711d194f8d4a99171cddcd-fr" start="20260312212404 +0000" stop="20260314212404 +0000">
        <title>Two Warriors : le combat du siècle</title>
        <desc>Tokyo, peu après la 2nde Guerre Mondiale. Un champion de boxe japonais jusque là invaincu se prépare à affronter un challenger américain.</desc>
        <icon src="https://images.pluto.tv/episodes/68711d194f8d4a99171cddcd/screenshot16_9_1768332965074.jpg?fill=blur&amp;fit=fill&amp;fm=jpg&amp;h=540&amp;q=75&amp;w=960"/>
    </programme>
    <programme channel="68ad5037b76cf0ad37f781fd-fr" start="20260312212404 +0000" stop="20260314212404 +0000">
        <title>L'Affaire Monet</title>
        <desc>Un célèbre faussaire accepte un marché avec la mafia : voler un Monet contre une remise de peine. Pour ce coup risqué, il réunit une équipe inattendue : son père et son fils.</desc>
        <icon src="https://images.pluto.tv/episodes/68ad5037b76cf0ad37f781fd/screenshot16_9_1758874526583.jpg?fill=blur&amp;fit=fill&amp;fm=jpg&amp;h=540&amp;q=75&amp;w=960"/>
    </programme>
    <programme channel="68711d1c4f8d4a99171d4f8e-fr" start="20260312212404 +0000" stop="20260314212404 +0000">
        <title>Jane</title>
        <desc>Olivia, brisée par la perte d’un ami et un refus d’université, sombre dans des crises de panique. Pour reprendre le contrôle, elle se déchaîne sur les réseaux sociaux contre ceux qui freinent ses rêves.</desc>
        <icon src="https://images.pluto.tv/episodes/68711d1c4f8d4a99171d4f8e/screenshot16_9_1768332963227.jpg?fill=blur&amp;fit=fill&amp;fm=jpg&amp;h=540&amp;q=75&amp;w=960"/>
    </programme>
    <programme channel="6871177f8eef10068fbddb38-fr" start="20260312212404 +0000" stop="20260314212404 +0000">
        <title>Burn</title>
        <desc>Melinda, jeune employée d'une station service, est fatiguée de vivre dans l'ombre de Sheila. Quand le jeune Billy vient braquer l'établissement, Melinda profite de l'occasion pour se mettre du côté de l'agresseur et inverser le rapport de force.</desc>
        <icon src="https://images.pluto.tv/episodes/6871177f8eef10068fbddb38/screenshot16_9_1768265643414.jpg?fill=blur&amp;fit=fill&amp;fm=jpg&amp;h=540&amp;q=75&amp;w=960"/>
    </programme>
    <programme channel="68ad5031b76cf0ad37f69d9b-fr" start="20260312212404 +0000" stop="20260314212404 +0000">
        <title>2040</title>
        <desc>Après Sugarland, Damon Gameau explore des solutions écologiques méconnues pour préserver l’avenir des enfants. Du Massachusetts à d'autres lieux innovants, il rencontre ceux qui agissent concrètement pour lutter contre le réchauffement climatique.</desc>
        <icon src="https://images.pluto.tv/episodes/68ad5031b76cf0ad37f69d9b/screenshot16_9_1768422965282.jpg?fill=blur&amp;fit=fill&amp;fm=jpg&amp;h=540&amp;q=75&amp;w=960"/>
    </programme>
    <programme channel="68936b5199a2f3e74a0f58a1-fr" start="20260312212404 +0000" stop="20260314212404 +0000">
        <title>Party Girl</title>
        <desc>Dans cette comédie mouvementée, Parker Posey joue le rôle d'une fêtarde invétérée de NY qui prend un emploi de bibliothécaire.</desc>
        <icon src="https://images.pluto.tv/episodes/68936b5199a2f3e74a0f58a1/screenshot16_9_1768346785913.jpg?fill=blur&amp;fit=fill&amp;fm=jpg&amp;h=540&amp;q=75&amp;w=960"/>
    </programme>
    <programme channel="68944d89cb15389834479443-fr" start="20260312212404 +0000" stop="20260314212404 +0000">
        <title>Sprinter</title>
        <desc>Un jeune Jamaïcain, dont la vie est marquée par une figure paternelle incertaine et un aîné rebelle, rêve que son succès en athlétisme lui permettra de retrouver sa mère, qui réside illégalement aux États-Unis depuis plus de 10 ans.</desc>
        <icon src="https://images.pluto.tv/episodes/68944d89cb15389834479443/screenshot16_9_1768331890429.jpg?fill=blur&amp;fit=fill&amp;fm=jpg&amp;h=540&amp;q=75&amp;w=960"/>
    </programme>
    <programme channel="68944d8ccb1538983447f634-fr" start="20260312212404 +0000" stop="20260314212404 +0000">
        <title>Les arnaqueurs</title>
        <desc>Un arnaqueur de bas étage (John Cusack) voit sa loyauté mise à l'épreuve par la mère qui l'a abandonné (Anjelica Huston) et sa nouvelle petite-amie (Annette Bening), toutes les deux des escrocs de grand calibre avec leurs propres objectifs.</desc>
        <icon src="https://images.pluto.tv/episodes/68944d8ccb1538983447f634/screenshot16_9_1768337999892.jpg?fill=blur&amp;fit=fill&amp;fm=jpg&amp;h=540&amp;q=75&amp;w=960"/>
    </programme>
    <programme channel="68944d93cb1538983448ca9d-fr" start="20260312212404 +0000" stop="20260314212404 +0000">
        <title>MVP</title>
        <desc>Dans les rues d'Hollywood, un joueur de la NFL récemment retraité est sauvé d'un scandale par un vétéran sans-abri. Les jours de gloire passés, les deux hommes se lient à la recherche d'un but et d'une identité.</desc>
        <icon src="https://images.pluto.tv/episodes/68944d93cb1538983448ca9d/screenshot16_9_1754549654041.jpg?fill=blur&amp;fit=fill&amp;fm=jpg&amp;h=540&amp;q=75&amp;w=960"/>
    </programme>
    <programme channel="68944c32cb15389834473242-fr" start="20260312212404 +0000" stop="20260314212404 +0000">
        <title>The Short History of the Long Road</title>
        <desc>Ce documentaire explore la vie de Melissa Lucio, la première femme Hispanique condamnée à mort au Texas. Elle a attendu son sort pendant dix ans, et maintenant elle fait face à son dernier appel.</desc>
        <icon src="https://images.pluto.tv/episodes/68944c32cb15389834473242/screenshot16_9_1754549362390.jpg?fill=blur&amp;fit=fill&amp;fm=jpg&amp;h=540&amp;q=75&amp;w=960"/>
    </programme>
    <programme channel="68936ca6fd92ab53e88171c4-fr" start="20260312212404 +0000" stop="20260314212404 +0000">
        <title>Inuit</title>
        <desc>Un pilote et son passager luttent pour survivre après un accident dans la toundra Arctique.</desc>
        <icon src="https://images.pluto.tv/episodes/68936ca6fd92ab53e88171c4/screenshot16_9_1754492072156.jpg?fill=blur&amp;fit=fill&amp;fm=jpg&amp;h=540&amp;q=75&amp;w=960"/>
    </programme>
    <programme channel="6895f201baa646038d362302-fr" start="20260312212404 +0000" stop="20260314212404 +0000">
        <title>Jean de la Fontaine, le défi</title>
        <desc>Paris, 1661. Alors que tous les artistes du royaume de France cherchent à entrer dans les bonnes grâces du roi Soleil, Jean de La Fontaine n’hésite pas à dénoncer les abus du pouvoir.</desc>
        <icon src="https://images.pluto.tv/episodes/6895f201baa646038d362302/screenshot16_9_1754657282800.jpg?fill=blur&amp;fit=fill&amp;fm=jpg&amp;h=540&amp;q=75&amp;w=960"/>
    </programme>
    <programme channel="68944d96cb15389834492c8e-fr" start="20260312212404 +0000" stop="20260314212404 +0000">
        <title>Voltaire et l'affaire Calas</title>
        <desc>Un homme d'affaires protestant, Jean Calas, est torturé à mort pour avoir prétendument tué son fils afin de l'empêcher de devenir catholique.</desc>
        <icon src="https://images.pluto.tv/episodes/68944d96cb15389834492c8e/screenshot16_9_1754549656251.jpg?fill=blur&amp;fit=fill&amp;fm=jpg&amp;h=540&amp;q=75&amp;w=960"/>
    </programme>
    <programme channel="68944d99cb15389834499f07-fr" start="20260312212404 +0000" stop="20260314212404 +0000">
        <title>Frères de sang</title>
        <desc>Martin, quinze ans, jure à Brice, son frère aîné accusé de quatre meurtres, de le sortir de prison. Armé de sa seule conviction, défiant ses parents et la police, l’adolescent se lance dans une terrifiante enquête.</desc>
        <icon src="https://images.pluto.tv/episodes/68944d99cb15389834499f07/screenshot16_9_1754549670718.jpg?fill=blur&amp;fit=fill&amp;fm=jpg&amp;h=540&amp;q=75&amp;w=960"/>
    </programme>
    <programme channel="68936ca0fd92ab53e8809de9-fr" start="20260312212404 +0000" stop="20260314212404 +0000">
        <title>Une place parmi les vivants</title>
        <desc>Paris, 7 Janvier 1958. Ernest Ripper vient d'apprendre le refus du manuscrit de son premier roman "Le Jugement Dernier". Il se rend au "Lapin Chasseur" où l'attend un mystérieux admirateur qui insiste pour le rencontrer.</desc>
        <icon src="https://images.pluto.tv/episodes/68936ca0fd92ab53e8809de9/screenshot16_9_1754492066962.jpg?fill=blur&amp;fit=fill&amp;fm=jpg&amp;h=540&amp;q=75&amp;w=960"/>
    </programme>
    <programme channel="686b6f0931b6562298c1e843-fr" start="20260312212404 +0000" stop="20260314212404 +0000">
        <title>Une Star Dans Ma Vie</title>
        <desc>Une star hollywoodienne tente de mettre fin à sa traversée du désert en acceptant un rôle dans une petite production. Pour s'imprégner de son personnage de gérant de supermarché, il se rend dans un quartier populaire de Los Angeles. Là, il fait la connaissance de Scarlet, une caissière malheureuse. Il tombe sous son charme et décide de l'aider.</desc>
        <icon src="https://images.pluto.tv/episodes/686b6f0931b6562298c1e843/screenshot16_9_1751871244698.jpg?fill=blur&amp;fit=fill&amp;fm=jpg&amp;h=540&amp;q=75&amp;w=960"/>
    </programme>
</tv>